{"$schema":"http://cyclonedx.org/schema/bom-1.5.schema.json","bomFormat":"CycloneDX","specVersion":"1.5","serialNumber":"urn:uuid:a4adb0f5-8e8c-43af-bfa7-42fc7aa540d8","version":1,"metadata":{"timestamp":"2024-08-23T13:05:20Z","tools":{"components":[{"type":"application","author":"anchore","name":"syft","version":"1.11.0"}]},"component":{"bom-ref":"02b4df51b6ec00c7","type":"file","name":"/tmp/repo-clone-1929085745"}},"components":[{"bom-ref":"pkg:github/actions/github-script@v7?package-id=f077e86626a5e436","type":"library","name":"actions/github-script","version":"v7","cpe":"cpe:2.3:a:actions\\/github-script:actions\\/github-script:v7:*:*:*:*:*:*:*","purl":"pkg:github/actions/github-script@v7","properties":[{"name":"syft:package:foundBy","value":"github-actions-usage-cataloger"},{"name":"syft:package:type","value":"github-action"},{"name":"syft:cpe23","value":"cpe:2.3:a:actions\\/github-script:actions\\/github_script:v7:*:*:*:*:*:*:*"},{"name":"syft:cpe23","value":"cpe:2.3:a:actions\\/github_script:actions\\/github-script:v7:*:*:*:*:*:*:*"},{"name":"syft:cpe23","value":"cpe:2.3:a:actions\\/github_script:actions\\/github_script:v7:*:*:*:*:*:*:*"},{"name":"syft:cpe23","value":"cpe:2.3:a:actions\\/github:actions\\/github-script:v7:*:*:*:*:*:*:*"},{"name":"syft:cpe23","value":"cpe:2.3:a:actions\\/github:actions\\/github_script:v7:*:*:*:*:*:*:*"},{"name":"syft:location:0:path","value":"/.github/workflows/issue.yml"}]},{"bom-ref":"pkg:golang/github.com/gabriel-vasile/mimetype@v1.4.3?package-id=ed271496b40ae290","type":"library","name":"github.com/gabriel-vasile/mimetype","version":"v1.4.3","cpe":"cpe:2.3:a:gabriel-vasile:mimetype:v1.4.3:*:*:*:*:*:*:*","purl":"pkg:golang/github.com/gabriel-vasile/mimetype@v1.4.3","properties":[{"name":"syft:package:foundBy","value":"go-module-file-cataloger"},{"name":"syft:package:language","value":"go"},{"name":"syft:package:type","value":"go-module"},{"name":"syft:package:metadataType","value":"go-module-entry"},{"name":"syft:cpe23","value":"cpe:2.3:a:gabriel_vasile:mimetype:v1.4.3:*:*:*:*:*:*:*"},{"name":"syft:cpe23","value":"cpe:2.3:a:gabriel:mimetype:v1.4.3:*:*:*:*:*:*:*"},{"name":"syft:location:0:path","value":"/go.mod"},{"name":"syft:metadata:h1Digest","value":"h1:in2uUcidCuFcDKtdcBxlR0rJ1+fsokWf+uqxgUFjbI0="}]},{"bom-ref":"pkg:golang/github.com/go-playground/locales@v0.14.1?package-id=0ab483711ac82dec","type":"library","name":"github.com/go-playground/locales","version":"v0.14.1","cpe":"cpe:2.3:a:go-playground:locales:v0.14.1:*:*:*:*:*:*:*","purl":"pkg:golang/github.com/go-playground/locales@v0.14.1","properties":[{"name":"syft:package:foundBy","value":"go-module-file-cataloger"},{"name":"syft:package:language","value":"go"},{"name":"syft:package:type","value":"go-module"},{"name":"syft:package:metadataType","value":"go-module-entry"},{"name":"syft:cpe23","value":"cpe:2.3:a:go_playground:locales:v0.14.1:*:*:*:*:*:*:*"},{"name":"syft:cpe23","value":"cpe:2.3:a:go:locales:v0.14.1:*:*:*:*:*:*:*"},{"name":"syft:location:0:path","value":"/go.mod"},{"name":"syft:metadata:h1Digest","value":"h1:EWaQ/wswjilfKLTECiXz7Rh+3BjFhfDFKv/oXslEjJA="}]},{"bom-ref":"pkg:golang/github.com/go-playground/universal-translator@v0.18.1?package-id=aa3c8c1e33334216","type":"library","name":"github.com/go-playground/universal-translator","version":"v0.18.1","cpe":"cpe:2.3:a:go-playground:universal-translator:v0.18.1:*:*:*:*:*:*:*","purl":"pkg:golang/github.com/go-playground/universal-translator@v0.18.1","properties":[{"name":"syft:package:foundBy","value":"go-module-file-cataloger"},{"name":"syft:package:language","value":"go"},{"name":"syft:package:type","value":"go-module"},{"name":"syft:package:metadataType","value":"go-module-entry"},{"name":"syft:cpe23","value":"cpe:2.3:a:go-playground:universal_translator:v0.18.1:*:*:*:*:*:*:*"},{"name":"syft:cpe23","value":"cpe:2.3:a:go_playground:universal-translator:v0.18.1:*:*:*:*:*:*:*"},{"name":"syft:cpe23","value":"cpe:2.3:a:go_playground:universal_translator:v0.18.1:*:*:*:*:*:*:*"},{"name":"syft:cpe23","value":"cpe:2.3:a:go:universal-translator:v0.18.1:*:*:*:*:*:*:*"},{"name":"syft:cpe23","value":"cpe:2.3:a:go:universal_translator:v0.18.1:*:*:*:*:*:*:*"},{"name":"syft:location:0:path","value":"/go.mod"},{"name":"syft:metadata:h1Digest","value":"h1:Bcnm0ZwsGyWbCzImXv+pAJnYK9S473LQFuzCbDbfSFY="}]},{"bom-ref":"pkg:golang/github.com/go-playground/validator@v10.22.0?package-id=22a19e284742d307#v10","type":"library","name":"github.com/go-playground/validator/v10","version":"v10.22.0","cpe":"cpe:2.3:a:go-playground:validator\\/v10:v10.22.0:*:*:*:*:*:*:*","purl":"pkg:golang/github.com/go-playground/validator@v10.22.0#v10","properties":[{"name":"syft:package:foundBy","value":"go-module-file-cataloger"},{"name":"syft:package:language","value":"go"},{"name":"syft:package:type","value":"go-module"},{"name":"syft:package:metadataType","value":"go-module-entry"},{"name":"syft:cpe23","value":"cpe:2.3:a:go_playground:validator\\/v10:v10.22.0:*:*:*:*:*:*:*"},{"name":"syft:cpe23","value":"cpe:2.3:a:go:validator\\/v10:v10.22.0:*:*:*:*:*:*:*"},{"name":"syft:location:0:path","value":"/go.mod"},{"name":"syft:metadata:h1Digest","value":"h1:k6HsTZ0sTnROkhS//R0O+55JgM8C4Bx7ia+JlgcnOao="}]},{"bom-ref":"pkg:golang/github.com/leodido/go-urn@v1.4.0?package-id=dc31b61b5d1d57b8","type":"library","name":"github.com/leodido/go-urn","version":"v1.4.0","cpe":"cpe:2.3:a:leodido:go-urn:v1.4.0:*:*:*:*:*:*:*","purl":"pkg:golang/github.com/leodido/go-urn@v1.4.0","properties":[{"name":"syft:package:foundBy","value":"go-module-file-cataloger"},{"name":"syft:package:language","value":"go"},{"name":"syft:package:type","value":"go-module"},{"name":"syft:package:metadataType","value":"go-module-entry"},{"name":"syft:cpe23","value":"cpe:2.3:a:leodido:go_urn:v1.4.0:*:*:*:*:*:*:*"},{"name":"syft:location:0:path","value":"/go.mod"},{"name":"syft:metadata:h1Digest","value":"h1:WT9HwE9SGECu3lg4d/dIA+jxlljEa1/ffXKmRjqdmIQ="}]},{"bom-ref":"pkg:golang/golang.org/x/crypto@v0.22.0?package-id=bd4f7f6ad36e1077","type":"library","name":"golang.org/x/crypto","version":"v0.22.0","cpe":"cpe:2.3:a:golang:x\\/crypto:v0.22.0:*:*:*:*:*:*:*","purl":"pkg:golang/golang.org/x/crypto@v0.22.0","properties":[{"name":"syft:package:foundBy","value":"go-module-file-cataloger"},{"name":"syft:package:language","value":"go"},{"name":"syft:package:type","value":"go-module"},{"name":"syft:package:metadataType","value":"go-module-entry"},{"name":"syft:location:0:path","value":"/go.mod"},{"name":"syft:metadata:h1Digest","value":"h1:g1v0xeRhjcugydODzvb3mEM9SQ0HGp9s/nh3COQ/C30="}]},{"bom-ref":"pkg:golang/golang.org/x/net@v0.24.0?package-id=450ba5eb30997783","type":"library","name":"golang.org/x/net","version":"v0.24.0","cpe":"cpe:2.3:a:golang:networking:v0.24.0:*:*:*:*:go:*:*","purl":"pkg:golang/golang.org/x/net@v0.24.0","properties":[{"name":"syft:package:foundBy","value":"go-module-file-cataloger"},{"name":"syft:package:language","value":"go"},{"name":"syft:package:type","value":"go-module"},{"name":"syft:package:metadataType","value":"go-module-entry"},{"name":"syft:location:0:path","value":"/go.mod"},{"name":"syft:metadata:h1Digest","value":"h1:1PcaxkF854Fu3+lvBIx5SYn9wRlBzzcnHZSiaFFAb0w="}]},{"bom-ref":"pkg:golang/golang.org/x/sys@v0.19.0?package-id=2d5e062090be5d09","type":"library","name":"golang.org/x/sys","version":"v0.19.0","cpe":"cpe:2.3:a:golang:x\\/sys:v0.19.0:*:*:*:*:*:*:*","purl":"pkg:golang/golang.org/x/sys@v0.19.0","properties":[{"name":"syft:package:foundBy","value":"go-module-file-cataloger"},{"name":"syft:package:language","value":"go"},{"name":"syft:package:type","value":"go-module"},{"name":"syft:package:metadataType","value":"go-module-entry"},{"name":"syft:location:0:path","value":"/go.mod"},{"name":"syft:metadata:h1Digest","value":"h1:q5f1RH2jigJ1MoAWp2KTp3gm5zAGFUTarQZ5U386+4o="}]},{"bom-ref":"pkg:golang/golang.org/x/text@v0.14.0?package-id=c70ce8df32c6f44e","type":"library","name":"golang.org/x/text","version":"v0.14.0","cpe":"cpe:2.3:a:golang:text:v0.14.0:*:*:*:*:*:*:*","purl":"pkg:golang/golang.org/x/text@v0.14.0","properties":[{"name":"syft:package:foundBy","value":"go-module-file-cataloger"},{"name":"syft:package:language","value":"go"},{"name":"syft:package:type","value":"go-module"},{"name":"syft:package:metadataType","value":"go-module-entry"},{"name":"syft:location:0:path","value":"/go.mod"},{"name":"syft:metadata:h1Digest","value":"h1:ScX5w1eTa3QqT8oi6+ziP7dTV1S2+ALU0bI+0zXKWiQ="}]}]}
