{"bomFormat":"CycloneDX","specVersion":"1.5","serialNumber":"urn:uuid:a74baf9d-c752-4787-9330-dcf8ff019e0d","version":1,"metadata":{"timestamp":"2024-08-14T11:07:56Z","tools":{"components":[{"group":"@cyclonedx","name":"cdxgen","version":"10.9.2","purl":"pkg:npm/%40cyclonedx/cdxgen@10.9.2","type":"application","bom-ref":"pkg:npm/@cyclonedx/cdxgen@10.9.2","author":"OWASP Foundation","publisher":"OWASP Foundation"}]},"authors":[{"name":"OWASP Foundation"}],"lifecycles":[{"phase":"build"}],"component":{"group":"","name":"repo-clone-3033008121","version":"latest","type":"application","bom-ref":"pkg:gem/repo-clone-3033008121@latest","purl":"pkg:gem/repo-clone-3033008121@latest"},"properties":[{"name":"cdx:bom:componentTypes","value":"github\\ngolang"},{"name":"cdx:bom:componentNamespaces","value":"actions\\namannn\\ncloud.google.com\\ncloud.google.com/go\\ncloud.google.com/go/compute\\ncosmossdk.io\\ncosmossdk.io/client\\ncosmossdk.io/x\\nfilippo.io\\ngaurav-nelson\\ngithub.com/99designs\\ngithub.com/BurntSushi\\ngithub.com/ChainSafe\\ngithub.com/ComposableFi/go-subkey\\ngithub.com/DataDog\\ngithub.com/FactomProject\\ngithub.com/Microsoft\\ngithub.com/OneOfOne\\ngithub.com/StirlingMarketingGroup\\ngithub.com/avast/retry-go\\ngithub.com/aws\\ngithub.com/beorn7\\ngithub.com/bgentry\\ngithub.com/bits-and-blooms\\ngithub.com/btcsuite\\ngithub.com/btcsuite/btcd\\ngithub.com/btcsuite/btcd/btcec\\ngithub.com/btcsuite/btcd/chaincfg\\ngithub.com/cenkalti/backoff\\ngithub.com/cespare\\ngithub.com/cespare/xxhash\\ngithub.com/chzyer\\ngithub.com/cockroachdb\\ngithub.com/cockroachdb/apd\\ngithub.com/cometbft\\ngithub.com/consensys\\ngithub.com/containerd\\ngithub.com/cosmos\\ngithub.com/cosmos/ibc-go\\ngithub.com/cosmos/ibc-go/modules\\ngithub.com/cosmos/ics23\\ngithub.com/crate-crypto\\ngithub.com/danieljoos\\ngithub.com/davecgh\\ngithub.com/deckarep\\ngithub.com/decred\\ngithub.com/decred/dcrd/crypto\\ngithub.com/decred/dcrd/dcrec/secp256k1\\ngithub.com/desertbit\\ngithub.com/dgraph-io\\ngithub.com/dgraph-io/badger\\ngithub.com/dgryski\\ngithub.com/docker\\ngithub.com/dustin\\ngithub.com/dvsekhvalnov\\ngithub.com/emicklei\\ngithub.com/ethereum\\ngithub.com/fatih\\ngithub.com/felixge\\ngithub.com/fsnotify\\ngithub.com/getsentry\\ngithub.com/go-kit\\ngithub.com/go-logfmt\\ngithub.com/go-logr\\ngithub.com/godbus\\ngithub.com/gofrs\\ngithub.com/gogo\\ngithub.com/golang\\ngithub.com/google\\ngithub.com/google/go-github\\ngithub.com/googleapis\\ngithub.com/googleapis/gax-go\\ngithub.com/gorilla\\ngithub.com/grpc-ecosystem\\ngithub.com/gsterjov\\ngithub.com/gtank\\ngithub.com/hashicorp\\ngithub.com/hdevalence\\ngithub.com/holiman\\ngithub.com/huandu\\ngithub.com/iancoleman\\ngithub.com/icza\\ngithub.com/improbable-eng\\ngithub.com/inconshreveable\\ngithub.com/ipfs\\ngithub.com/jmespath\\ngithub.com/jmhodges\\ngithub.com/jsternberg\\ngithub.com/kballard\\ngithub.com/klauspost\\ngithub.com/klauspost/cpuid\\ngithub.com/kr\\ngithub.com/lib\\ngithub.com/libp2p\\ngithub.com/linxGnu\\ngithub.com/magiconair\\ngithub.com/manifoldco\\ngithub.com/mattn\\ngithub.com/mimoo\\ngithub.com/minio\\ngithub.com/misko9/go-substrate-rpc-client\\ngithub.com/mitchellh\\ngithub.com/mmcloughlin\\ngithub.com/moby\\ngithub.com/moby/sys\\ngithub.com/mr-tron\\ngithub.com/mtibben\\ngithub.com/multiformats\\ngithub.com/oasisprotocol\\ngithub.com/oklog\\ngithub.com/opencontainers\\ngithub.com/pelletier\\ngithub.com/pelletier/go-toml\\ngithub.com/petermattis\\ngithub.com/pierrec\\ngithub.com/pkg\\ngithub.com/pmezard\\ngithub.com/prometheus\\ngithub.com/rcrowley\\ngithub.com/regen-network\\ngithub.com/remyoudompheng\\ngithub.com/rogpeppe\\ngithub.com/rs\\ngithub.com/sagikazarmark\\ngithub.com/sasha-s\\ngithub.com/sirupsen\\ngithub.com/sourcegraph\\ngithub.com/spaolacci\\ngithub.com/spf13\\ngithub.com/strangelove-ventures\\ngithub.com/strangelove-ventures/interchaintest\\ngithub.com/stretchr\\ngithub.com/subosito\\ngithub.com/supranational\\ngithub.com/syndtr\\ngithub.com/tendermint\\ngithub.com/tidwall\\ngithub.com/tyler-smith\\ngithub.com/ulikunitz\\ngithub.com/zondax\\ngo.etcd.io\\ngo.opentelemetry.io\\ngo.opentelemetry.io/contrib/instrumentation/google.golang.org/grpc\\ngo.opentelemetry.io/contrib/instrumentation/net/http\\ngo.opentelemetry.io/otel\\ngo.uber.org\\ngolang.org/x\\ngoogle.golang.org\\ngoogle.golang.org/genproto/googleapis\\ngopkg.in\\ngopkg.in/natefinch\\ngotest.tools\\nlukechampine.com\\nmodernc.org\\nmodernc.org/cc\\nmodernc.org/ccgo\\nnhooyr.io\\npgregory.net\\nrsc.io\\nsigs.k8s.io"}]},"components":[{"group":"","name":"cosmossdk.io/api","version":"v0.7.3","hashes":[{"alg":"SHA-256","content":"21cc69612e5f31e9991aac98b44acaeceaaf74cd02f24756dddabc43f5c81b7f"}],"purl":"pkg:golang/cosmossdk.io/api@v0.7.3","type":"library","bom-ref":"pkg:golang/cosmossdk.io/api@v0.7.3"},{"group":"","name":"cosmossdk.io/errors","version":"v1.0.1","hashes":[{"alg":"SHA-256","content":"31e7a555265384c8b86c46a4ce186113f08aa95bf79ce243036e5b22a443bbf5"}],"purl":"pkg:golang/cosmossdk.io/errors@v1.0.1","type":"library","bom-ref":"pkg:golang/cosmossdk.io/errors@v1.0.1"},{"group":"","name":"cosmossdk.io/math","version":"v1.3.0","hashes":[{"alg":"SHA-256","content":"be7453c5ec32f8cec1b5704d1726e4ba1487e167de7550009c4447815161a779"}],"purl":"pkg:golang/cosmossdk.io/math@v1.3.0","type":"library","bom-ref":"pkg:golang/cosmossdk.io/math@v1.3.0"},{"group":"","name":"cosmossdk.io/store","version":"v1.0.2","hashes":[{"alg":"SHA-256","content":"105b44353a954ee5b08ad196d55c1a05cb7ec836a093ba06fdac4130f1fe157b"}],"purl":"pkg:golang/cosmossdk.io/store@v1.0.2","type":"library","bom-ref":"pkg:golang/cosmossdk.io/store@v1.0.2"},{"group":"","name":"cosmossdk.io/x/feegrant","version":"v0.1.0","hashes":[{"alg":"SHA-256","content":"e2bf85b1588946971989fff28539fe13413a3857e0e27d0bc7ee9c0ad9d91255"}],"purl":"pkg:golang/cosmossdk.io/x/feegrant@v0.1.0","type":"library","bom-ref":"pkg:golang/cosmossdk.io/x/feegrant@v0.1.0"},{"group":"","name":"cosmossdk.io/x/tx","version":"v0.13.1","hashes":[{"alg":"SHA-256","content":"081094e9fb11573db74061484016f50cd5f60f3b4909fde35b21241d8da7250d"}],"purl":"pkg:golang/cosmossdk.io/x/tx@v0.13.1","type":"library","bom-ref":"pkg:golang/cosmossdk.io/x/tx@v0.13.1"},{"group":"","name":"cosmossdk.io/x/upgrade","version":"v0.1.1","hashes":[{"alg":"SHA-256","content":"30d2e9b4b3dc2052bd096b7b45affff16519031c1ec910cd71bb399e439c432d"}],"purl":"pkg:golang/cosmossdk.io/x/upgrade@v0.1.1","type":"library","bom-ref":"pkg:golang/cosmossdk.io/x/upgrade@v0.1.1"},{"group":"","name":"github.com/avast/retry-go/v4","version":"v4.5.1","hashes":[{"alg":"SHA-256","content":"fec8a936cbcd077451b93e6235c6fa87bde7c3720199727f1f75eb0906123a97"}],"purl":"pkg:golang/github.com/avast/retry-go/v4@v4.5.1","type":"library","bom-ref":"pkg:golang/github.com/avast/retry-go/v4@v4.5.1"},{"group":"","name":"github.com/btcsuite/btcd","version":"v0.24.0","hashes":[{"alg":"SHA-256","content":"2b8203735e7ddecf23297205ef24bbc824d2c6b92707dcf4493cdcda3e97804e"}],"purl":"pkg:golang/github.com/btcsuite/btcd@v0.24.0","type":"library","bom-ref":"pkg:golang/github.com/btcsuite/btcd@v0.24.0"},{"group":"","name":"github.com/btcsuite/btcd/btcutil","version":"v1.1.5","hashes":[{"alg":"SHA-256","content":"3d2659e148ada4b056cf119de5518eacb9e63a3b4f3ff6ba1da168d76cccb34d"}],"purl":"pkg:golang/github.com/btcsuite/btcd/btcutil@v1.1.5","type":"library","bom-ref":"pkg:golang/github.com/btcsuite/btcd/btcutil@v1.1.5"},{"group":"","name":"github.com/cometbft/cometbft","version":"v0.38.6","hashes":[{"alg":"SHA-256","content":"f2b48fc7350962ab8237cbae0606d41ce320d8a030bebec2c94c3eeae90ee27c"}],"purl":"pkg:golang/github.com/cometbft/cometbft@v0.38.6","type":"library","bom-ref":"pkg:golang/github.com/cometbft/cometbft@v0.38.6"},{"group":"","name":"github.com/cosmos/cosmos-proto","version":"v1.0.0-beta.4","hashes":[{"alg":"SHA-256","content":"a1e07e1725731b75eb4096c99e0d049d5f159637e4f57bd32291882cd53ff42a"}],"purl":"pkg:golang/github.com/cosmos/cosmos-proto@v1.0.0-beta.4","type":"library","bom-ref":"pkg:golang/github.com/cosmos/cosmos-proto@v1.0.0-beta.4"},{"group":"","name":"github.com/cosmos/cosmos-sdk","version":"v0.50.5","hashes":[{"alg":"SHA-256","content":"a15fe4e862605d5f503e83367ec6033cfb323c18106dda2dbf9df63ba333d4e4"}],"purl":"pkg:golang/github.com/cosmos/cosmos-sdk@v0.50.5","type":"framework","bom-ref":"pkg:golang/github.com/cosmos/cosmos-sdk@v0.50.5"},{"group":"","name":"github.com/cosmos/go-bip39","version":"v1.0.0","hashes":[{"alg":"SHA-256","content":"44d26fd07fe9388560c70e8a4bb41e5f66b4528d1a29495f859e31bb0bc2749c"}],"purl":"pkg:golang/github.com/cosmos/go-bip39@v1.0.0","type":"library","bom-ref":"pkg:golang/github.com/cosmos/go-bip39@v1.0.0"},{"group":"","name":"github.com/cosmos/gogoproto","version":"v1.4.11","hashes":[{"alg":"SHA-256","content":"fe0dfd321f26d7b5fc43f18312ce7361348d68d9c89c14a886d6b1cd09d8ab56"}],"purl":"pkg:golang/github.com/cosmos/gogoproto@v1.4.11","type":"library","bom-ref":"pkg:golang/github.com/cosmos/gogoproto@v1.4.11"},{"group":"","name":"github.com/cosmos/ibc-go/modules/capability","version":"v1.0.0","hashes":[{"alg":"SHA-256","content":"0fcd59c738d901ed193b96a66e7be7d6a79db0543c94ec2daa2706ea588b05ca"}],"purl":"pkg:golang/github.com/cosmos/ibc-go/modules/capability@v1.0.0","type":"library","bom-ref":"pkg:golang/github.com/cosmos/ibc-go/modules/capability@v1.0.0"},{"group":"","name":"github.com/cosmos/ibc-go/v8","version":"v8.2.0","hashes":[{"alg":"SHA-256","content":"c23deac7be620bf5cd9ec32a6cf0c2206b341ba63713f968ddb76a0b2a02cbef"}],"purl":"pkg:golang/github.com/cosmos/ibc-go/v8@v8.2.0","type":"library","bom-ref":"pkg:golang/github.com/cosmos/ibc-go/v8@v8.2.0"},{"group":"","name":"github.com/cosmos/ics23/go","version":"v0.10.0","hashes":[{"alg":"SHA-256","content":"65f2529a783f4c135306415e9871c78f9618ed5014fcc054f7cd05e15535346d"}],"purl":"pkg:golang/github.com/cosmos/ics23/go@v0.10.0","type":"library","bom-ref":"pkg:golang/github.com/cosmos/ics23/go@v0.10.0"},{"group":"","name":"github.com/ethereum/go-ethereum","version":"v1.13.15","hashes":[{"alg":"SHA-256","content":"4cdf19887add27049ef026fac7ea7486ce42c612593dba81ee11e46945dc9885"}],"purl":"pkg:golang/github.com/ethereum/go-ethereum@v1.13.15","type":"library","bom-ref":"pkg:golang/github.com/ethereum/go-ethereum@v1.13.15"},{"group":"","name":"github.com/gofrs/flock","version":"v0.8.1","hashes":[{"alg":"SHA-256","content":"1754ef4e22bd39c42a6ae3541e56c9bf297d41ad50bc5fe03940ca035e23c475"}],"purl":"pkg:golang/github.com/gofrs/flock@v0.8.1","type":"library","bom-ref":"pkg:golang/github.com/gofrs/flock@v0.8.1"},{"group":"","name":"github.com/google/go-github/v43","version":"v43.0.0","hashes":[{"alg":"SHA-256","content":"6644efbe609706fb1f3e94c75e71ff77684ff58d1c4dbbcdf64af9c6ac973887"}],"purl":"pkg:golang/github.com/google/go-github/v43@v43.0.0","type":"library","bom-ref":"pkg:golang/github.com/google/go-github/v43@v43.0.0"},{"group":"","name":"github.com/grpc-ecosystem/grpc-gateway","version":"v1.16.0","hashes":[{"alg":"SHA-256","content":"0438eb424de16ef8fa368960cfc9803056dc12d8d3d60fb017809296872b067c"}],"purl":"pkg:golang/github.com/grpc-ecosystem/grpc-gateway@v1.16.0","type":"library","bom-ref":"pkg:golang/github.com/grpc-ecosystem/grpc-gateway@v1.16.0"},{"group":"","name":"github.com/jsternberg/zap-logfmt","version":"v1.3.0","hashes":[{"alg":"SHA-256","content":"3770c4369f56366099c6f9010ff791796c33d75e3d04aea310df5c4387cdc191"}],"purl":"pkg:golang/github.com/jsternberg/zap-logfmt@v1.3.0","type":"library","bom-ref":"pkg:golang/github.com/jsternberg/zap-logfmt@v1.3.0"},{"group":"","name":"github.com/prometheus/client_golang","version":"v1.18.0","hashes":[{"alg":"SHA-256","content":"4fe197902939c122723aa308cd582fbe31439643909ed82390958aacde6dc630"}],"purl":"pkg:golang/github.com/prometheus/client_golang@v1.18.0","type":"library","bom-ref":"pkg:golang/github.com/prometheus/client_golang@v1.18.0"},{"group":"","name":"github.com/spf13/cobra","version":"v1.8.0","hashes":[{"alg":"SHA-256","content":"5972d60297d9ef50235cfc9add63a532c63dc8cb3b61e887845565bcbca1721a"}],"purl":"pkg:golang/github.com/spf13/cobra@v1.8.0","type":"library","bom-ref":"pkg:golang/github.com/spf13/cobra@v1.8.0"},{"group":"","name":"github.com/spf13/viper","version":"v1.18.2","hashes":[{"alg":"SHA-256","content":"10a99622a76793994e72647bdb2c3a852fbc38f61cc03d23b5e8ad2cc541fb29"}],"purl":"pkg:golang/github.com/spf13/viper@v1.18.2","type":"library","bom-ref":"pkg:golang/github.com/spf13/viper@v1.18.2"},{"group":"","name":"github.com/strangelove-ventures/cometbft-client","version":"v0.1.0","hashes":[{"alg":"SHA-256","content":"4334e1823cefb0681435536918f8ad9b1396308869e9ad28a9ff349c244db7fd"}],"purl":"pkg:golang/github.com/strangelove-ventures/cometbft-client@v0.1.0","type":"library","bom-ref":"pkg:golang/github.com/strangelove-ventures/cometbft-client@v0.1.0"},{"group":"","name":"github.com/stretchr/testify","version":"v1.9.0","hashes":[{"alg":"SHA-256","content":"af689cfe5a9ecff944b732fbc0efebc1ae5d6d22d75433c5c9ff02f758b7e9a6"}],"purl":"pkg:golang/github.com/stretchr/testify@v1.9.0","type":"library","bom-ref":"pkg:golang/github.com/stretchr/testify@v1.9.0"},{"group":"","name":"github.com/tyler-smith/go-bip39","version":"v1.1.0","hashes":[{"alg":"SHA-256","content":"814603b6a430d494b7649f145957064c6aaaafa60837709683e92435a2ede795"}],"purl":"pkg:golang/github.com/tyler-smith/go-bip39@v1.1.0","type":"library","bom-ref":"pkg:golang/github.com/tyler-smith/go-bip39@v1.1.0"},{"group":"","name":"go.uber.org/multierr","version":"v1.10.0","hashes":[{"alg":"SHA-256","content":"db4f90b622eacb435de8575007d4cb5da835d83b1092b6ecde1b4c15f0cdf346"}],"purl":"pkg:golang/go.uber.org/multierr@v1.10.0","type":"library","bom-ref":"pkg:golang/go.uber.org/multierr@v1.10.0"},{"group":"","name":"go.uber.org/zap","version":"v1.26.0","hashes":[{"alg":"SHA-256","content":"76d125b6d022c06be827fbe3e08c07052fe05ec12efe9679d26508456b86d2ca"}],"purl":"pkg:golang/go.uber.org/zap@v1.26.0","type":"library","bom-ref":"pkg:golang/go.uber.org/zap@v1.26.0"},{"group":"","name":"golang.org/x/sync","version":"v0.6.0","hashes":[{"alg":"SHA-256","content":"0b3b7ec0abb5802c8414352d9f48c6e5056fa49eabcd5aabe5a5f2b7d76b41f9"}],"purl":"pkg:golang/golang.org/x/sync@v0.6.0","type":"library","bom-ref":"pkg:golang/golang.org/x/sync@v0.6.0"},{"group":"","name":"golang.org/x/text","version":"v0.14.0","hashes":[{"alg":"SHA-256","content":"d7c64e4082a963c34956a624b0a1ed4dd8b7d47e62b45463079fea293358cd25"}],"purl":"pkg:golang/golang.org/x/text@v0.14.0","type":"library","bom-ref":"pkg:golang/golang.org/x/text@v0.14.0"},{"group":"","name":"google.golang.org/grpc","version":"v1.62.1","hashes":[{"alg":"SHA-256","content":"2164c6d159492c28754a40b9f05ee7a7d91af66c7f58d9239783c625a8aaf901"}],"purl":"pkg:golang/google.golang.org/grpc@v1.62.1","type":"library","bom-ref":"pkg:golang/google.golang.org/grpc@v1.62.1"},{"group":"","name":"gopkg.in/yaml.v2","version":"v2.4.0","hashes":[{"alg":"SHA-256","content":"4439256e4efd0065a6c219efb7f8c1ced6a910e1833b1e996d7aa33fa72c1a74"}],"purl":"pkg:golang/gopkg.in/yaml.v2@v2.4.0","type":"library","bom-ref":"pkg:golang/gopkg.in/yaml.v2@v2.4.0"},{"group":"","name":"gopkg.in/yaml.v3","version":"v3.0.1","hashes":[{"alg":"SHA-256","content":"2b8bb293bcfb04210faaee84f82eb861fbf5710ee4cfbac866f89498df848043"}],"purl":"pkg:golang/gopkg.in/yaml.v3@v3.0.1","type":"library","bom-ref":"pkg:golang/gopkg.in/yaml.v3@v3.0.1"},{"group":"","name":"cloud.google.com/go","version":"v0.112.0","hashes":[{"alg":"SHA-256","content":"de310457067f3075387632b9b79447b8a380fc66cb75d813755b9b5f5aa73c3e"}],"purl":"pkg:golang/cloud.google.com/go@v0.112.0","type":"library","bom-ref":"pkg:golang/cloud.google.com/go@v0.112.0"},{"group":"","name":"cloud.google.com/go/compute","version":"v1.24.0","hashes":[{"alg":"SHA-256","content":"930d7f4fe87ffad2b62c92b4c223cfc758a7b607403378ff8378450e5b1c638d"}],"purl":"pkg:golang/cloud.google.com/go/compute@v1.24.0","type":"library","bom-ref":"pkg:golang/cloud.google.com/go/compute@v1.24.0"},{"group":"","name":"cloud.google.com/go/compute/metadata","version":"v0.2.3","hashes":[{"alg":"SHA-256","content":"5405799d2b000b1309be0680b97e8f93601ac25667f2488e1ae0afea04e4c2e0"}],"purl":"pkg:golang/cloud.google.com/go/compute/metadata@v0.2.3","type":"library","bom-ref":"pkg:golang/cloud.google.com/go/compute/metadata@v0.2.3"},{"group":"","name":"cloud.google.com/go/iam","version":"v1.1.6","hashes":[{"alg":"SHA-256","content":"3b4cf174f78606815d596dc75a607126c934a5fbcd33fa7fa9af36ad63864f02"}],"purl":"pkg:golang/cloud.google.com/go/iam@v1.1.6","type":"library","bom-ref":"pkg:golang/cloud.google.com/go/iam@v1.1.6"},{"group":"","name":"cloud.google.com/go/storage","version":"v1.36.0","hashes":[{"alg":"SHA-256","content":"33a33fdd5fc3dcaa733132723ce47f1d4ea7d928b941d697604b27836c603acf"}],"purl":"pkg:golang/cloud.google.com/go/storage@v1.36.0","type":"library","bom-ref":"pkg:golang/cloud.google.com/go/storage@v1.36.0"},{"group":"","name":"cosmossdk.io/collections","version":"v0.4.0","hashes":[{"alg":"SHA-256","content":"a1ae65508346d9d3fe81d0eaba8c3e423945e3978bd6de13243ca980677eb6fd"}],"purl":"pkg:golang/cosmossdk.io/collections@v0.4.0","type":"library","bom-ref":"pkg:golang/cosmossdk.io/collections@v0.4.0"},{"group":"","name":"cosmossdk.io/core","version":"v0.11.0","hashes":[{"alg":"SHA-256","content":"2da4ed6b25814a869c179c4dce817cb662e17a1aa503dcf549688fb8d0ba5f5c"}],"purl":"pkg:golang/cosmossdk.io/core@v0.11.0","type":"library","bom-ref":"pkg:golang/cosmossdk.io/core@v0.11.0"},{"group":"","name":"cosmossdk.io/depinject","version":"v1.0.0-alpha.4","hashes":[{"alg":"SHA-256","content":"1de0e4ec8911e5c919de5306b3fa3dd4055473b139f7abcc68e9ac94614cdf25"}],"purl":"pkg:golang/cosmossdk.io/depinject@v1.0.0-alpha.4","type":"library","bom-ref":"pkg:golang/cosmossdk.io/depinject@v1.0.0-alpha.4"},{"group":"","name":"cosmossdk.io/log","version":"v1.3.1","hashes":[{"alg":"SHA-256","content":"dbf748a26b7c98a764eaf97739625c3e4d9b7b7a46392f0e41a2d433fdffb423"}],"purl":"pkg:golang/cosmossdk.io/log@v1.3.1","type":"library","bom-ref":"pkg:golang/cosmossdk.io/log@v1.3.1"},{"group":"","name":"filippo.io/edwards25519","version":"v1.0.0","hashes":[{"alg":"SHA-256","content":"3752247640a488b07ab648be3182684b1d894d8f4d525c5913b7879f9130267b"}],"purl":"pkg:golang/filippo.io/edwards25519@v1.0.0","type":"library","bom-ref":"pkg:golang/filippo.io/edwards25519@v1.0.0"},{"group":"","name":"github.com/99designs/go-keychain","version":"v0.0.0-20191008050251-8e49817e8af4","hashes":[{"alg":"SHA-256","content":"84dee86884428f3b19d9d13ec86e64fabb1db77a9cc3292a2ba1d519c2b0b30e"}],"purl":"pkg:golang/github.com/99designs/go-keychain@v0.0.0-20191008050251-8e49817e8af4","type":"library","bom-ref":"pkg:golang/github.com/99designs/go-keychain@v0.0.0-20191008050251-8e49817e8af4"},{"group":"","name":"github.com/99designs/keyring","version":"v1.2.1","hashes":[{"alg":"SHA-256","content":"7dcfb007929393dc10f6c0f1d2415707703431a7861ccf40c114ad28e439bce0"}],"purl":"pkg:golang/github.com/99designs/keyring@v1.2.1","type":"library","bom-ref":"pkg:golang/github.com/99designs/keyring@v1.2.1"},{"group":"","name":"github.com/DataDog/datadog-go","version":"v3.2.0+incompatible","hashes":[{"alg":"SHA-256","content":"2c1badc60e4fc1111e66d391a171b7b4be1f30635d749faf32ad66c207daaa84"}],"purl":"pkg:golang/github.com/DataDog/datadog-go@v3.2.0%2Bincompatible","type":"library","bom-ref":"pkg:golang/github.com/DataDog/datadog-go@v3.2.0+incompatible"},{"group":"","name":"github.com/DataDog/zstd","version":"v1.5.5","hashes":[{"alg":"SHA-256","content":"83801611a337c8e8371d87e72776086b03e755d5c987d40c13ce5b9704809b2c"}],"purl":"pkg:golang/github.com/DataDog/zstd@v1.5.5","type":"library","bom-ref":"pkg:golang/github.com/DataDog/zstd@v1.5.5"},{"group":"","name":"github.com/aws/aws-sdk-go","version":"v1.44.312","hashes":[{"alg":"SHA-256","content":"695b2041c11ebf096643ba8713d23787e76d420a6a84507e8bc3e18e1edf9302"}],"purl":"pkg:golang/github.com/aws/aws-sdk-go@v1.44.312","type":"framework","bom-ref":"pkg:golang/github.com/aws/aws-sdk-go@v1.44.312"},{"group":"","name":"github.com/beorn7/perks","version":"v1.0.1","hashes":[{"alg":"SHA-256","content":"1b666b55653659b593f70c2ae3f86b6ca6e7bffd44452250d226e127aae5929c"}],"purl":"pkg:golang/github.com/beorn7/perks@v1.0.1","type":"library","bom-ref":"pkg:golang/github.com/beorn7/perks@v1.0.1"},{"group":"","name":"github.com/bgentry/go-netrc","version":"v0.0.0-20140422174119-9fd32a8b3d3d","hashes":[{"alg":"SHA-256","content":"e905ff3d7674d33fd32a8b9f118e8afdad24e8085a26b40a7457ba39f557b1ae"}],"purl":"pkg:golang/github.com/bgentry/go-netrc@v0.0.0-20140422174119-9fd32a8b3d3d","type":"library","bom-ref":"pkg:golang/github.com/bgentry/go-netrc@v0.0.0-20140422174119-9fd32a8b3d3d"},{"group":"","name":"github.com/bgentry/speakeasy","version":"v0.1.1-0.20220910012023-760eaf8b6816","hashes":[{"alg":"SHA-256","content":"fb3b326413d6973ed3ea3f3c0938123796ccefde809157f49010f8ce9d02088b"}],"purl":"pkg:golang/github.com/bgentry/speakeasy@v0.1.1-0.20220910012023-760eaf8b6816","type":"library","bom-ref":"pkg:golang/github.com/bgentry/speakeasy@v0.1.1-0.20220910012023-760eaf8b6816"},{"group":"","name":"github.com/bits-and-blooms/bitset","version":"v1.10.0","hashes":[{"alg":"SHA-256","content":"ee13bb19cecfa75bce0dc996bca31103d04d99bbfa6bfed0216a4fc4775d591f"}],"purl":"pkg:golang/github.com/bits-and-blooms/bitset@v1.10.0","type":"library","bom-ref":"pkg:golang/github.com/bits-and-blooms/bitset@v1.10.0"},{"group":"","name":"github.com/btcsuite/btcd/btcec/v2","version":"v2.3.2","hashes":[{"alg":"SHA-256","content":"cd8cc9f1eb5625022fd4e824ecece95a3a30c0e7576355bfd7b8f6316f39274e"}],"purl":"pkg:golang/github.com/btcsuite/btcd/btcec/v2@v2.3.2","type":"library","bom-ref":"pkg:golang/github.com/btcsuite/btcd/btcec/v2@v2.3.2"},{"group":"","name":"github.com/btcsuite/btcd/chaincfg/chainhash","version":"v1.1.0","hashes":[{"alg":"SHA-256","content":"ed21646b45ccbd4823de17d9b7274ead06369b084f7256d3dac9e8814ed24107"}],"purl":"pkg:golang/github.com/btcsuite/btcd/chaincfg/chainhash@v1.1.0","type":"library","bom-ref":"pkg:golang/github.com/btcsuite/btcd/chaincfg/chainhash@v1.1.0"},{"group":"","name":"github.com/cenkalti/backoff/v4","version":"v4.1.3","hashes":[{"alg":"SHA-256","content":"b1c6ecb33f22646a66df16ebd78a2f954764c5f1973489ea90f58e5a61b608bc"}],"purl":"pkg:golang/github.com/cenkalti/backoff/v4@v4.1.3","type":"library","bom-ref":"pkg:golang/github.com/cenkalti/backoff/v4@v4.1.3"},{"group":"","name":"github.com/cespare/xxhash","version":"v1.1.0","hashes":[{"alg":"SHA-256","content":"5eb4aa47556aa967c6ae1a40b79f1ab91a34593292d674518378217c0a8f5a77"}],"purl":"pkg:golang/github.com/cespare/xxhash@v1.1.0","type":"library","bom-ref":"pkg:golang/github.com/cespare/xxhash@v1.1.0"},{"group":"","name":"github.com/cespare/xxhash/v2","version":"v2.2.0","hashes":[{"alg":"SHA-256","content":"5465f40d0dd0ea45a2ec0a007990ed877fe3dc116d3994795cb14681cae308eb"}],"purl":"pkg:golang/github.com/cespare/xxhash/v2@v2.2.0","type":"library","bom-ref":"pkg:golang/github.com/cespare/xxhash/v2@v2.2.0"},{"group":"","name":"github.com/chzyer/readline","version":"v1.5.1","hashes":[{"alg":"SHA-256","content":"121f9befd5d75307ca7dc3cb7a992cbf0dad70b13f0addb560e6e469291e0659"}],"purl":"pkg:golang/github.com/chzyer/readline@v1.5.1","type":"library","bom-ref":"pkg:golang/github.com/chzyer/readline@v1.5.1"},{"group":"","name":"github.com/cockroachdb/errors","version":"v1.11.1","hashes":[{"alg":"SHA-256","content":"f0c5310371a2e9bdb9b5894510118b7fe0fc68848bf8ce0c2298963123517f1c"}],"purl":"pkg:golang/github.com/cockroachdb/errors@v1.11.1","type":"library","bom-ref":"pkg:golang/github.com/cockroachdb/errors@v1.11.1"},{"group":"","name":"github.com/cockroachdb/logtags","version":"v0.0.0-20230118201751-21c54148d20b","hashes":[{"alg":"SHA-256","content":"573f43b155904217f7becdb53213cc6693064a1b7b3bfdaf156db1bac15454eb"}],"purl":"pkg:golang/github.com/cockroachdb/logtags@v0.0.0-20230118201751-21c54148d20b","type":"library","bom-ref":"pkg:golang/github.com/cockroachdb/logtags@v0.0.0-20230118201751-21c54148d20b"},{"group":"","name":"github.com/cockroachdb/pebble","version":"v1.1.0","hashes":[{"alg":"SHA-256","content":"b041e6e4d397c72880a0a5a1a05c53f3132077f7f7440eaa52a4350572ab8761"}],"purl":"pkg:golang/github.com/cockroachdb/pebble@v1.1.0","type":"library","bom-ref":"pkg:golang/github.com/cockroachdb/pebble@v1.1.0"},{"group":"","name":"github.com/cockroachdb/redact","version":"v1.1.5","hashes":[{"alg":"SHA-256","content":"05535b94df66056172332a8ad64dc00224b186f85f2b6a0e659da52be769bd18"}],"purl":"pkg:golang/github.com/cockroachdb/redact@v1.1.5","type":"library","bom-ref":"pkg:golang/github.com/cockroachdb/redact@v1.1.5"},{"group":"","name":"github.com/cockroachdb/tokenbucket","version":"v0.0.0-20230807174530-cc333fc44b06","hashes":[{"alg":"SHA-256","content":"ee77386a72c68eea545bf3de639aa2358b1d3578fbce8a46f9eaac4bb4e8e484"}],"purl":"pkg:golang/github.com/cockroachdb/tokenbucket@v0.0.0-20230807174530-cc333fc44b06","type":"library","bom-ref":"pkg:golang/github.com/cockroachdb/tokenbucket@v0.0.0-20230807174530-cc333fc44b06"},{"group":"","name":"github.com/cometbft/cometbft-db","version":"v0.9.1","hashes":[{"alg":"SHA-256","content":"8a58b259aa15d26470049a22cc4942c30440f537fb8d924e511711645f66eb45"}],"purl":"pkg:golang/github.com/cometbft/cometbft-db@v0.9.1","type":"library","bom-ref":"pkg:golang/github.com/cometbft/cometbft-db@v0.9.1"},{"group":"","name":"github.com/consensys/bavard","version":"v0.1.13","hashes":[{"alg":"SHA-256","content":"f48b5232d03f75730088bec11ba6ea5b69b735d48439b616a07db6de7187ba42"}],"purl":"pkg:golang/github.com/consensys/bavard@v0.1.13","type":"library","bom-ref":"pkg:golang/github.com/consensys/bavard@v0.1.13"},{"group":"","name":"github.com/consensys/gnark-crypto","version":"v0.12.1","hashes":[{"alg":"SHA-256","content":"bf61b2ecbff8651a2c67b22fb3ef527d40ebd1fe54946f84339b7b30f1e22ee6"}],"purl":"pkg:golang/github.com/consensys/gnark-crypto@v0.12.1","type":"library","bom-ref":"pkg:golang/github.com/consensys/gnark-crypto@v0.12.1"},{"group":"","name":"github.com/cosmos/btcutil","version":"v1.0.5","hashes":[{"alg":"SHA-256","content":"23207b8aea9930996d85edad90814bdf7c4fcb36c560fd1755d4bc3f99543e2b"}],"purl":"pkg:golang/github.com/cosmos/btcutil@v1.0.5","type":"library","bom-ref":"pkg:golang/github.com/cosmos/btcutil@v1.0.5"},{"group":"","name":"github.com/cosmos/cosmos-db","version":"v1.0.2","hashes":[{"alg":"SHA-256","content":"67c21770527d3ea28ae8122c54e077417b642a8a943a9d6f46f3d3dfd90e5c40"}],"purl":"pkg:golang/github.com/cosmos/cosmos-db@v1.0.2","type":"library","bom-ref":"pkg:golang/github.com/cosmos/cosmos-db@v1.0.2"},{"group":"","name":"github.com/cosmos/gogogateway","version":"v1.2.0","hashes":[{"alg":"SHA-256","content":"890a4b9065b161c9c2773e6201d2dc4414b0de1ecd5de3a4678194913fad6c52"}],"purl":"pkg:golang/github.com/cosmos/gogogateway@v1.2.0","type":"library","bom-ref":"pkg:golang/github.com/cosmos/gogogateway@v1.2.0"},{"group":"","name":"github.com/cosmos/iavl","version":"v1.0.1","hashes":[{"alg":"SHA-256","content":"f3121492056fc2f56b06ef35b1c74fb72fbf0f1f46ab01e702f5f3e1cc05ed16"}],"purl":"pkg:golang/github.com/cosmos/iavl@v1.0.1","type":"library","bom-ref":"pkg:golang/github.com/cosmos/iavl@v1.0.1"},{"group":"","name":"github.com/cosmos/ledger-cosmos-go","version":"v0.13.3","hashes":[{"alg":"SHA-256","content":"1c435c10ff95b5a859170dfc1d9dfe2d2dc8bf95d5eacbec9e493dbdd26d2ebf"}],"purl":"pkg:golang/github.com/cosmos/ledger-cosmos-go@v0.13.3","type":"library","bom-ref":"pkg:golang/github.com/cosmos/ledger-cosmos-go@v0.13.3"},{"group":"","name":"github.com/crate-crypto/go-kzg-4844","version":"v0.7.0","hashes":[{"alg":"SHA-256","content":"d64321bcf808d0acb7c886bef65172484054057918c5e3a2f19175b188a8c617"}],"purl":"pkg:golang/github.com/crate-crypto/go-kzg-4844@v0.7.0","type":"library","bom-ref":"pkg:golang/github.com/crate-crypto/go-kzg-4844@v0.7.0"},{"group":"","name":"github.com/danieljoos/wincred","version":"v1.1.2","hashes":[{"alg":"SHA-256","content":"1a28e9ce289f2682017d887e4bb05b91d5135382df33e4271aa479565dad031d"}],"purl":"pkg:golang/github.com/danieljoos/wincred@v1.1.2","type":"library","bom-ref":"pkg:golang/github.com/danieljoos/wincred@v1.1.2"},{"group":"","name":"github.com/davecgh/go-spew","version":"v1.1.2-0.20180830191138-d8f796af33cc","hashes":[{"alg":"SHA-256","content":"27b63c61c5b636286c826568fe6bf7940c25fec90e37888b1e34ac23e7391f7f"}],"purl":"pkg:golang/github.com/davecgh/go-spew@v1.1.2-0.20180830191138-d8f796af33cc","type":"library","bom-ref":"pkg:golang/github.com/davecgh/go-spew@v1.1.2-0.20180830191138-d8f796af33cc"},{"group":"","name":"github.com/decred/dcrd/dcrec/secp256k1/v4","version":"v4.2.0","hashes":[{"alg":"SHA-256","content":"bf9ed40c5e290d025c11f154091a29de524bd78f5e1c649ef49bdcce1ce3a3fd"}],"purl":"pkg:golang/github.com/decred/dcrd/dcrec/secp256k1/v4@v4.2.0","type":"library","bom-ref":"pkg:golang/github.com/decred/dcrd/dcrec/secp256k1/v4@v4.2.0"},{"group":"","name":"github.com/desertbit/timer","version":"v0.0.0-20180107155436-c41aec40b27f","hashes":[{"alg":"SHA-256","content":"c47fe2e1314cb7c92855067a5859acebd580b035abd97b182f71e497b8e4a0b1"}],"purl":"pkg:golang/github.com/desertbit/timer@v0.0.0-20180107155436-c41aec40b27f","type":"library","bom-ref":"pkg:golang/github.com/desertbit/timer@v0.0.0-20180107155436-c41aec40b27f"},{"group":"","name":"github.com/dgraph-io/badger/v2","version":"v2.2007.4","hashes":[{"alg":"SHA-256","content":"bd2c3f6b1daaa23cdb37a7971c8c7a28f2ad0921c937f533d17d153ebb932219"}],"purl":"pkg:golang/github.com/dgraph-io/badger/v2@v2.2007.4","type":"library","bom-ref":"pkg:golang/github.com/dgraph-io/badger/v2@v2.2007.4"},{"group":"","name":"github.com/dgraph-io/ristretto","version":"v0.1.1","hashes":[{"alg":"SHA-256","content":"4b518f48109808886654d7dcb61d7bcb6cd9b504fac3393383052f7b45435960"}],"purl":"pkg:golang/github.com/dgraph-io/ristretto@v0.1.1","type":"library","bom-ref":"pkg:golang/github.com/dgraph-io/ristretto@v0.1.1"},{"group":"","name":"github.com/dgryski/go-farm","version":"v0.0.0-20200201041132-a6ae2369ad13","hashes":[{"alg":"SHA-256","content":"4aa52b38f527b058df99744c34fc9b712886d018145b602e147f0f0274b6893c"}],"purl":"pkg:golang/github.com/dgryski/go-farm@v0.0.0-20200201041132-a6ae2369ad13","type":"library","bom-ref":"pkg:golang/github.com/dgryski/go-farm@v0.0.0-20200201041132-a6ae2369ad13"},{"group":"","name":"github.com/dustin/go-humanize","version":"v1.0.1","hashes":[{"alg":"SHA-256","content":"32ed7322ce97c15b85fe023539ea6f234a83d7cab2710c7e985ca48797c196da"}],"purl":"pkg:golang/github.com/dustin/go-humanize@v1.0.1","type":"library","bom-ref":"pkg:golang/github.com/dustin/go-humanize@v1.0.1"},{"group":"","name":"github.com/dvsekhvalnov/jose2go","version":"v1.6.0","hashes":[{"alg":"SHA-256","content":"42c1e38724e50ff94056a9ff3526d566648219e0de85307f98f65a746fa68575"}],"purl":"pkg:golang/github.com/dvsekhvalnov/jose2go@v1.6.0","type":"library","bom-ref":"pkg:golang/github.com/dvsekhvalnov/jose2go@v1.6.0"},{"group":"","name":"github.com/emicklei/dot","version":"v1.6.1","hashes":[{"alg":"SHA-256","content":"0de57b1af42d230e21daeef744a06490576f540cf40fd7f3789ae03d6ea0cbfb"}],"purl":"pkg:golang/github.com/emicklei/dot@v1.6.1","type":"library","bom-ref":"pkg:golang/github.com/emicklei/dot@v1.6.1"},{"group":"","name":"github.com/ethereum/c-kzg-4844","version":"v0.4.0","hashes":[{"alg":"SHA-256","content":"55ec1d973426a53e504ab5616c1b86a02745264a5a2653b5690a6eb4ff37c1cd"}],"purl":"pkg:golang/github.com/ethereum/c-kzg-4844@v0.4.0","type":"library","bom-ref":"pkg:golang/github.com/ethereum/c-kzg-4844@v0.4.0"},{"group":"","name":"github.com/fatih/color","version":"v1.15.0","hashes":[{"alg":"SHA-256","content":"d21e59a977c76040fb061bf66496a6c883947a3f4ab52862244491c010d44acc"}],"purl":"pkg:golang/github.com/fatih/color@v1.15.0","type":"library","bom-ref":"pkg:golang/github.com/fatih/color@v1.15.0"},{"group":"","name":"github.com/felixge/httpsnoop","version":"v1.0.4","hashes":[{"alg":"SHA-256","content":"9bc28f24aaa4d601f927d0e0458d804a5da55827c62978b14b07af79af331f65"}],"purl":"pkg:golang/github.com/felixge/httpsnoop@v1.0.4","type":"library","bom-ref":"pkg:golang/github.com/felixge/httpsnoop@v1.0.4"},{"group":"","name":"github.com/fsnotify/fsnotify","version":"v1.7.0","hashes":[{"alg":"SHA-256","content":"e34062fc78dcd8055f66bab2f9a8fec8423efdb471667309c932703a91af8a03"}],"purl":"pkg:golang/github.com/fsnotify/fsnotify@v1.7.0","type":"library","bom-ref":"pkg:golang/github.com/fsnotify/fsnotify@v1.7.0"},{"group":"","name":"github.com/getsentry/sentry-go","version":"v0.27.0","hashes":[{"alg":"SHA-256","content":"95cefa136432c08c96f16b819f097c2dce1b926407e3ec358304dfdb9b6ba6b6"}],"purl":"pkg:golang/github.com/getsentry/sentry-go@v0.27.0","type":"library","bom-ref":"pkg:golang/github.com/getsentry/sentry-go@v0.27.0"},{"group":"","name":"github.com/go-kit/kit","version":"v0.12.0","hashes":[{"alg":"SHA-256","content":"94777e1240993c8c1822d9860c345d8629e4cd7d80d6c8fe33d6e26846a2cf3b"}],"purl":"pkg:golang/github.com/go-kit/kit@v0.12.0","type":"library","bom-ref":"pkg:golang/github.com/go-kit/kit@v0.12.0"},{"group":"","name":"github.com/go-kit/log","version":"v0.2.1","hashes":[{"alg":"SHA-256","content":"3704ddd3477f8bc70f677c4ec308afd8f3b930e731efc7c512b18d7159818efd"}],"purl":"pkg:golang/github.com/go-kit/log@v0.2.1","type":"library","bom-ref":"pkg:golang/github.com/go-kit/log@v0.2.1"},{"group":"","name":"github.com/go-logfmt/logfmt","version":"v0.6.0","hashes":[{"alg":"SHA-256","content":"59886d22ef334d97f1767e7ead111db986f0c5f701aff56be8a115bde5a57d3b"}],"purl":"pkg:golang/github.com/go-logfmt/logfmt@v0.6.0","type":"library","bom-ref":"pkg:golang/github.com/go-logfmt/logfmt@v0.6.0"},{"group":"","name":"github.com/go-logr/logr","version":"v1.4.1","hashes":[{"alg":"SHA-256","content":"f53d74e06cf2ad38a0148afcc2de6606b72d1cc8a6d0d6f61cb1ab990e342af6"}],"purl":"pkg:golang/github.com/go-logr/logr@v1.4.1","type":"library","bom-ref":"pkg:golang/github.com/go-logr/logr@v1.4.1"},{"group":"","name":"github.com/go-logr/stdr","version":"v1.2.2","hashes":[{"alg":"SHA-256","content":"98ca3fbed04ee5d61b7a1444a1ecba5d42b2fde4ae9a3082bde0e946b7b854a1"}],"purl":"pkg:golang/github.com/go-logr/stdr@v1.2.2","type":"library","bom-ref":"pkg:golang/github.com/go-logr/stdr@v1.2.2"},{"group":"","name":"github.com/godbus/dbus","version":"v0.0.0-20190726142602-4481cbc300e2","hashes":[{"alg":"SHA-256","content":"6c13808701b5ba637affa65432d0c504c411f23460f4eef9b66f4ad34a0cb0ae"}],"purl":"pkg:golang/github.com/godbus/dbus@v0.0.0-20190726142602-4481cbc300e2","type":"library","bom-ref":"pkg:golang/github.com/godbus/dbus@v0.0.0-20190726142602-4481cbc300e2"},{"group":"","name":"github.com/gogo/googleapis","version":"v1.4.1","hashes":[{"alg":"SHA-256","content":"da5a47a88e4e7160ad5449715e73edfacf2826f329c9294ec8ceb10c2af389be"}],"purl":"pkg:golang/github.com/gogo/googleapis@v1.4.1","type":"library","bom-ref":"pkg:golang/github.com/gogo/googleapis@v1.4.1"},{"group":"","name":"github.com/gogo/protobuf","version":"v1.3.2","hashes":[{"alg":"SHA-256","content":"3f55e2383ddd0b020a5034183f2ef60fc2d8c872f660f62ba52dacebd35957c4"}],"purl":"pkg:golang/github.com/gogo/protobuf@v1.3.2","type":"library","bom-ref":"pkg:golang/github.com/gogo/protobuf@v1.3.2"},{"group":"","name":"github.com/golang/glog","version":"v1.2.0","hashes":[{"alg":"SHA-256","content":"e80870486a61d1f709b5754cfcf1073ea66515ea0bc61b3bfede540c0c263bec"}],"purl":"pkg:golang/github.com/golang/glog@v1.2.0","type":"library","bom-ref":"pkg:golang/github.com/golang/glog@v1.2.0"},{"group":"","name":"github.com/golang/groupcache","version":"v0.0.0-20210331224755-41bb18bfe9da","hashes":[{"alg":"SHA-256","content":"7088387abb93ad7d43fa0f3c7f345753939d35f68cfbd21cc6c535e05cd8ec77"}],"purl":"pkg:golang/github.com/golang/groupcache@v0.0.0-20210331224755-41bb18bfe9da","type":"library","bom-ref":"pkg:golang/github.com/golang/groupcache@v0.0.0-20210331224755-41bb18bfe9da"},{"group":"","name":"github.com/golang/mock","version":"v1.6.0","hashes":[{"alg":"SHA-256","content":"a7ac933cffb91d89b99b3b0c57c26413a64a757fbfc1833a1ebf8b89c7af2cfb"}],"purl":"pkg:golang/github.com/golang/mock@v1.6.0","type":"library","bom-ref":"pkg:golang/github.com/golang/mock@v1.6.0"},{"group":"","name":"github.com/golang/protobuf","version":"v1.5.4","hashes":[{"alg":"SHA-256","content":"9674e22c0f166b845645c21492bb5255ae67461b04181838f1f0faad2b3bc69b"}],"purl":"pkg:golang/github.com/golang/protobuf@v1.5.4","type":"library","bom-ref":"pkg:golang/github.com/golang/protobuf@v1.5.4"},{"group":"","name":"github.com/golang/snappy","version":"v0.0.5-0.20220116011046-fa5810519dcb","hashes":[{"alg":"SHA-256","content":"fd7c5b7e6320f25c5e7ca33b2170b77c1365ffb6d171cef6682473116ae63f64"}],"purl":"pkg:golang/github.com/golang/snappy@v0.0.5-0.20220116011046-fa5810519dcb","type":"library","bom-ref":"pkg:golang/github.com/golang/snappy@v0.0.5-0.20220116011046-fa5810519dcb"},{"group":"","name":"github.com/google/btree","version":"v1.1.2","hashes":[{"alg":"SHA-256","content":"a8e3e14f475335d37357a67f961457d185d469f80f2c5521fa064c97beb51a6e"}],"purl":"pkg:golang/github.com/google/btree@v1.1.2","type":"library","bom-ref":"pkg:golang/github.com/google/btree@v1.1.2"},{"group":"","name":"github.com/google/go-cmp","version":"v0.6.0","hashes":[{"alg":"SHA-256","content":"d7b75496404e6a4274f8392b4923630a4223c52e9b17dcdbdde96678d1888e86"}],"purl":"pkg:golang/github.com/google/go-cmp@v0.6.0","type":"library","bom-ref":"pkg:golang/github.com/google/go-cmp@v0.6.0"},{"group":"","name":"github.com/google/go-querystring","version":"v1.1.0","hashes":[{"alg":"SHA-256","content":"29c76bd830789286b2abb5fca66006e2c346e7d4a8d7b89c452394eb6de55015"}],"purl":"pkg:golang/github.com/google/go-querystring@v1.1.0","type":"library","bom-ref":"pkg:golang/github.com/google/go-querystring@v1.1.0"},{"group":"","name":"github.com/google/orderedcode","version":"v0.0.1","hashes":[{"alg":"SHA-256","content":"895c94e3fa8f28763987fc1277aad96420dc2c93718963ba76fb18112d926f6d"}],"purl":"pkg:golang/github.com/google/orderedcode@v0.0.1","type":"library","bom-ref":"pkg:golang/github.com/google/orderedcode@v0.0.1"},{"group":"","name":"github.com/google/s2a-go","version":"v0.1.7","hashes":[{"alg":"SHA-256","content":"e740a04789358cd95606ee147d2e0071f8557b5afaa5d64fca027747c17441dc"}],"purl":"pkg:golang/github.com/google/s2a-go@v0.1.7","type":"library","bom-ref":"pkg:golang/github.com/google/s2a-go@v0.1.7"},{"group":"","name":"github.com/google/uuid","version":"v1.6.0","hashes":[{"alg":"SHA-256","content":"4c8c8f65ee0c82abdf7980c115e74ca061a9130fcba8e79a393fa787153ec87a"}],"purl":"pkg:golang/github.com/google/uuid@v1.6.0","type":"library","bom-ref":"pkg:golang/github.com/google/uuid@v1.6.0"},{"group":"","name":"github.com/googleapis/enterprise-certificate-proxy","version":"v0.3.2","hashes":[{"alg":"SHA-256","content":"54b4a249206cfe4b0f2fc92adce04e43a591236427685ca77750c28d9eb6f95d"}],"purl":"pkg:golang/github.com/googleapis/enterprise-certificate-proxy@v0.3.2","type":"library","bom-ref":"pkg:golang/github.com/googleapis/enterprise-certificate-proxy@v0.3.2"},{"group":"","name":"github.com/googleapis/gax-go/v2","version":"v2.12.0","hashes":[{"alg":"SHA-256","content":"cbe688aab23979bd5818c5497ee577d7ce53b3f0fba8aa6c124743e7e23a4065"}],"purl":"pkg:golang/github.com/googleapis/gax-go/v2@v2.12.0","type":"library","bom-ref":"pkg:golang/github.com/googleapis/gax-go/v2@v2.12.0"},{"group":"","name":"github.com/gorilla/handlers","version":"v1.5.2","hashes":[{"alg":"SHA-256","content":"757fb15696b1752c3eab441e93c492b25ddd7cc9378cd75d524333a341ad1f4c"}],"purl":"pkg:golang/github.com/gorilla/handlers@v1.5.2","type":"framework","bom-ref":"pkg:golang/github.com/gorilla/handlers@v1.5.2"},{"group":"","name":"github.com/gorilla/mux","version":"v1.8.1","hashes":[{"alg":"SHA-256","content":"00a7fd238004a8f4e6332b5c31cd0a90da2e0bae95dc1b59e2a0f97e659288c4"}],"purl":"pkg:golang/github.com/gorilla/mux@v1.8.1","type":"framework","bom-ref":"pkg:golang/github.com/gorilla/mux@v1.8.1"},{"group":"","name":"github.com/gorilla/websocket","version":"v1.5.1","hashes":[{"alg":"SHA-256","content":"c7790cd893326a5ba4d367e7509a50bb00f67424b93431b66472f4b84d2d71a6"}],"purl":"pkg:golang/github.com/gorilla/websocket@v1.5.1","type":"framework","bom-ref":"pkg:golang/github.com/gorilla/websocket@v1.5.1"},{"group":"","name":"github.com/grpc-ecosystem/go-grpc-middleware","version":"v1.4.0","hashes":[{"alg":"SHA-256","content":"839ab2a3f95ad002db38d9ba55ba7cf1877c36c0f2eab673f9172b30fc6f95df"}],"purl":"pkg:golang/github.com/grpc-ecosystem/go-grpc-middleware@v1.4.0","type":"library","bom-ref":"pkg:golang/github.com/grpc-ecosystem/go-grpc-middleware@v1.4.0"},{"group":"","name":"github.com/gsterjov/go-libsecret","version":"v0.0.0-20161001094733-a6f4afe4910c","hashes":[{"alg":"SHA-256","content":"34c3c9ca50e05695f430b4653f2d79b2a4b0385bff535199da6db526115f7a4d"}],"purl":"pkg:golang/github.com/gsterjov/go-libsecret@v0.0.0-20161001094733-a6f4afe4910c","type":"library","bom-ref":"pkg:golang/github.com/gsterjov/go-libsecret@v0.0.0-20161001094733-a6f4afe4910c"},{"group":"","name":"github.com/hashicorp/go-cleanhttp","version":"v0.5.2","hashes":[{"alg":"SHA-256","content":"90efd80e53fc2f5df8e84e92a1dc3e3eba41495e3f4a8c425c663a06a3454f8f"}],"purl":"pkg:golang/github.com/hashicorp/go-cleanhttp@v0.5.2","type":"library","bom-ref":"pkg:golang/github.com/hashicorp/go-cleanhttp@v0.5.2"},{"group":"","name":"github.com/hashicorp/go-getter","version":"v1.7.4","hashes":[{"alg":"SHA-256","content":"5bb4da9613266cf9ac48c74d8c3d19b24011babffd189d7b71f1d346d5d5ef8e"}],"purl":"pkg:golang/github.com/hashicorp/go-getter@v1.7.4","type":"library","bom-ref":"pkg:golang/github.com/hashicorp/go-getter@v1.7.4"},{"group":"","name":"github.com/hashicorp/go-hclog","version":"v1.5.0","hashes":[{"alg":"SHA-256","content":"5b8427bdbb7bd1693fcd826bc91cc3454ff8af49088343d51c171fa328691793"}],"purl":"pkg:golang/github.com/hashicorp/go-hclog@v1.5.0","type":"library","bom-ref":"pkg:golang/github.com/hashicorp/go-hclog@v1.5.0"},{"group":"","name":"github.com/hashicorp/go-immutable-radix","version":"v1.3.1","hashes":[{"alg":"SHA-256","content":"d32f6f6a7508f0d5fa16c6283b7cde323855fc2e62f60e10dc3c1c48d6783fad"}],"purl":"pkg:golang/github.com/hashicorp/go-immutable-radix@v1.3.1","type":"library","bom-ref":"pkg:golang/github.com/hashicorp/go-immutable-radix@v1.3.1"},{"group":"","name":"github.com/hashicorp/go-metrics","version":"v0.5.2","hashes":[{"alg":"SHA-256","content":"2848e875f79b20eb8161201efdb1d39be1c2866292c403973c189e30b628cc31"}],"purl":"pkg:golang/github.com/hashicorp/go-metrics@v0.5.2","type":"library","bom-ref":"pkg:golang/github.com/hashicorp/go-metrics@v0.5.2"},{"group":"","name":"github.com/hashicorp/go-plugin","version":"v1.5.2","hashes":[{"alg":"SHA-256","content":"c35b001044b78373ee57f47352b828c36d16dae12b325cbce21843dee9b558be"}],"purl":"pkg:golang/github.com/hashicorp/go-plugin@v1.5.2","type":"library","bom-ref":"pkg:golang/github.com/hashicorp/go-plugin@v1.5.2"},{"group":"","name":"github.com/hashicorp/go-safetemp","version":"v1.0.0","hashes":[{"alg":"SHA-256","content":"a1a7ab332dc186a8936d5c9ee90b85845b4871ea85a031f134007ae5bf918f52"}],"purl":"pkg:golang/github.com/hashicorp/go-safetemp@v1.0.0","type":"library","bom-ref":"pkg:golang/github.com/hashicorp/go-safetemp@v1.0.0"},{"group":"","name":"github.com/hashicorp/go-version","version":"v1.6.0","hashes":[{"alg":"SHA-256","content":"7e5b6be27f0253c29ee38c30182068132994bb1507974f5919564f2b96a7c170"}],"purl":"pkg:golang/github.com/hashicorp/go-version@v1.6.0","type":"library","bom-ref":"pkg:golang/github.com/hashicorp/go-version@v1.6.0"},{"group":"","name":"github.com/hashicorp/golang-lru","version":"v1.0.2","hashes":[{"alg":"SHA-256","content":"8800e64f0a882e8e2667c04ddc3d90ebef6377c58ce6e181c72f84f32c52a03e"}],"purl":"pkg:golang/github.com/hashicorp/golang-lru@v1.0.2","type":"library","bom-ref":"pkg:golang/github.com/hashicorp/golang-lru@v1.0.2"},{"group":"","name":"github.com/hashicorp/hcl","version":"v1.0.0","hashes":[{"alg":"SHA-256","content":"139c9f2e4fbbb308a6a5bd8bfc095bfcf2665e2950feb87069462ce13db45844"}],"purl":"pkg:golang/github.com/hashicorp/hcl@v1.0.0","type":"library","bom-ref":"pkg:golang/github.com/hashicorp/hcl@v1.0.0"},{"group":"","name":"github.com/hashicorp/yamux","version":"v0.1.1","hashes":[{"alg":"SHA-256","content":"0ad5850c04206fb771b7316ce2d59ba652887b68d28b7fb9bca6e020ed122e74"}],"purl":"pkg:golang/github.com/hashicorp/yamux@v0.1.1","type":"library","bom-ref":"pkg:golang/github.com/hashicorp/yamux@v0.1.1"},{"group":"","name":"github.com/hdevalence/ed25519consensus","version":"v0.1.0","hashes":[{"alg":"SHA-256","content":"c370475a3c096c5536f484472f522a930decbacfbb15cb44c8ce11a83c58373a"}],"purl":"pkg:golang/github.com/hdevalence/ed25519consensus@v0.1.0","type":"library","bom-ref":"pkg:golang/github.com/hdevalence/ed25519consensus@v0.1.0"},{"group":"","name":"github.com/holiman/uint256","version":"v1.2.4","hashes":[{"alg":"SHA-256","content":"10e3129f8aba372b7d3fa79f6c8ddbb9e5787b56f77469540977a2455e2783b1"}],"purl":"pkg:golang/github.com/holiman/uint256@v1.2.4","type":"library","bom-ref":"pkg:golang/github.com/holiman/uint256@v1.2.4"},{"group":"","name":"github.com/huandu/skiplist","version":"v1.2.0","hashes":[{"alg":"SHA-256","content":"eefde21632dc480ccee1f37907c76f79bbe8feab1fba688b8835ccacf88717dc"}],"purl":"pkg:golang/github.com/huandu/skiplist@v1.2.0","type":"library","bom-ref":"pkg:golang/github.com/huandu/skiplist@v1.2.0"},{"group":"","name":"github.com/iancoleman/strcase","version":"v0.3.0","hashes":[{"alg":"SHA-256","content":"8b00a6b5ef81ee7f3d7252b0c48a085f2fc77e82fb02c0f8ed9096858cf0ee1a"}],"purl":"pkg:golang/github.com/iancoleman/strcase@v0.3.0","type":"library","bom-ref":"pkg:golang/github.com/iancoleman/strcase@v0.3.0"},{"group":"","name":"github.com/improbable-eng/grpc-web","version":"v0.15.0","hashes":[{"alg":"SHA-256","content":"d6ccbd1ca57826df5a12cf494a791695124fb8fb7036bd25e7b2f87fcefcc0ff"}],"purl":"pkg:golang/github.com/improbable-eng/grpc-web@v0.15.0","type":"library","bom-ref":"pkg:golang/github.com/improbable-eng/grpc-web@v0.15.0"},{"group":"","name":"github.com/inconshreveable/mousetrap","version":"v1.1.0","hashes":[{"alg":"SHA-256","content":"be917bd055260bc6f06b73969c2b2177616a2dfb0403d3c5738c35a7627ae5bc"}],"purl":"pkg:golang/github.com/inconshreveable/mousetrap@v1.1.0","type":"library","bom-ref":"pkg:golang/github.com/inconshreveable/mousetrap@v1.1.0"},{"group":"","name":"github.com/jmespath/go-jmespath","version":"v0.4.0","hashes":[{"alg":"SHA-256","content":"4fc9896676ec6e617e9bacce385ca56de089aa4e7ea475afcd83f38b2662628a"}],"purl":"pkg:golang/github.com/jmespath/go-jmespath@v0.4.0","type":"library","bom-ref":"pkg:golang/github.com/jmespath/go-jmespath@v0.4.0"},{"group":"","name":"github.com/jmhodges/levigo","version":"v1.0.0","hashes":[{"alg":"SHA-256","content":"43a431fae1f7440ab22b8ac542ba2af512fb99d90004c71f84423e9cdbb33094"}],"purl":"pkg:golang/github.com/jmhodges/levigo@v1.0.0","type":"library","bom-ref":"pkg:golang/github.com/jmhodges/levigo@v1.0.0"},{"group":"","name":"github.com/klauspost/compress","version":"v1.17.7","hashes":[{"alg":"SHA-256","content":"0e2d1ea604e3258f3bede60ac79c82e75717d80d9597689b8bb6c31fdb6d05bc"}],"purl":"pkg:golang/github.com/klauspost/compress@v1.17.7","type":"library","bom-ref":"pkg:golang/github.com/klauspost/compress@v1.17.7"},{"group":"","name":"github.com/kr/pretty","version":"v0.3.1","hashes":[{"alg":"SHA-256","content":"86812c8585476b132cddcca8dd89dca2ee59b1c89fb83a25af03ca65a9c6df19"}],"purl":"pkg:golang/github.com/kr/pretty@v0.3.1","type":"library","bom-ref":"pkg:golang/github.com/kr/pretty@v0.3.1"},{"group":"","name":"github.com/kr/text","version":"v0.2.0","hashes":[{"alg":"SHA-256","content":"78b7abef6d937a4886b8c92274cc42fe9334e255847ab687514981c3c97682b1"}],"purl":"pkg:golang/github.com/kr/text@v0.2.0","type":"library","bom-ref":"pkg:golang/github.com/kr/text@v0.2.0"},{"group":"","name":"github.com/lib/pq","version":"v1.10.7","hashes":[{"alg":"SHA-256","content":"02554de71e04e13e78e2d5b31fa84a7db7d0be6dc775b3b1ae68200cd00f63da"}],"purl":"pkg:golang/github.com/lib/pq@v1.10.7","type":"library","bom-ref":"pkg:golang/github.com/lib/pq@v1.10.7"},{"group":"","name":"github.com/libp2p/go-buffer-pool","version":"v0.1.0","hashes":[{"alg":"SHA-256","content":"37ebe1f2032a8a607374a912315bb27550eaf945794135b2e474a265a7126cf8"}],"purl":"pkg:golang/github.com/libp2p/go-buffer-pool@v0.1.0","type":"library","bom-ref":"pkg:golang/github.com/libp2p/go-buffer-pool@v0.1.0"},{"group":"","name":"github.com/linxGnu/grocksdb","version":"v1.8.12","hashes":[{"alg":"SHA-256","content":"c590886f932ec3e9e16c32b8639509b8eae29f931c78eba25e455447bbe9e166"}],"purl":"pkg:golang/github.com/linxGnu/grocksdb@v1.8.12","type":"library","bom-ref":"pkg:golang/github.com/linxGnu/grocksdb@v1.8.12"},{"group":"","name":"github.com/magiconair/properties","version":"v1.8.7","hashes":[{"alg":"SHA-256","content":"0e177df395cfb3b8e5ba2ca6c16619d06e19eb58dbdef752df6f73863da1628d"}],"purl":"pkg:golang/github.com/magiconair/properties@v1.8.7","type":"library","bom-ref":"pkg:golang/github.com/magiconair/properties@v1.8.7"},{"group":"","name":"github.com/manifoldco/promptui","version":"v0.9.0","hashes":[{"alg":"SHA-256","content":"91ad38b29a71486140b715f4aa1958423212b20f66478196b5012175b9fa3e08"}],"purl":"pkg:golang/github.com/manifoldco/promptui@v0.9.0","type":"library","bom-ref":"pkg:golang/github.com/manifoldco/promptui@v0.9.0"},{"group":"","name":"github.com/mattn/go-colorable","version":"v0.1.13","hashes":[{"alg":"SHA-256","content":"ed2f7f7afd249600434781ad5d35d7f1adef206269328be407cbd07146da5c78"}],"purl":"pkg:golang/github.com/mattn/go-colorable@v0.1.13","type":"library","bom-ref":"pkg:golang/github.com/mattn/go-colorable@v0.1.13"},{"group":"","name":"github.com/mattn/go-isatty","version":"v0.0.20","hashes":[{"alg":"SHA-256","content":"5be57c3e5b534cc3af2af01e247ec8bae712f784b60ba8df2bf0fb753093a376"}],"purl":"pkg:golang/github.com/mattn/go-isatty@v0.0.20","type":"library","bom-ref":"pkg:golang/github.com/mattn/go-isatty@v0.0.20"},{"group":"","name":"github.com/minio/highwayhash","version":"v1.0.2","hashes":[{"alg":"SHA-256","content":"050b240eafb1909d76966954522ed4d0ce52c20dc4591f9d2d393e92576f5716"}],"purl":"pkg:golang/github.com/minio/highwayhash@v1.0.2","type":"library","bom-ref":"pkg:golang/github.com/minio/highwayhash@v1.0.2"},{"group":"","name":"github.com/mitchellh/go-homedir","version":"v1.1.0","hashes":[{"alg":"SHA-256","content":"49fc9a094a580a7d5595fe08518883f5f3d7e00e7026b90bcc8cf5375ab4a6bd"}],"purl":"pkg:golang/github.com/mitchellh/go-homedir@v1.1.0","type":"library","bom-ref":"pkg:golang/github.com/mitchellh/go-homedir@v1.1.0"},{"group":"","name":"github.com/mitchellh/go-testing-interface","version":"v1.14.1","hashes":[{"alg":"SHA-256","content":"81f812eceb598fa300e14d54ac3469d38b70a808dfbe567209f5f7b038c4ca6f"}],"purl":"pkg:golang/github.com/mitchellh/go-testing-interface@v1.14.1","type":"library","bom-ref":"pkg:golang/github.com/mitchellh/go-testing-interface@v1.14.1"},{"group":"","name":"github.com/mitchellh/mapstructure","version":"v1.5.0","hashes":[{"alg":"SHA-256","content":"6c552d56b280e030b6c802a24b23bf414732edef91455d904d63b384fa29051a"}],"purl":"pkg:golang/github.com/mitchellh/mapstructure@v1.5.0","type":"library","bom-ref":"pkg:golang/github.com/mitchellh/mapstructure@v1.5.0"},{"group":"","name":"github.com/mmcloughlin/addchain","version":"v0.4.0","hashes":[{"alg":"SHA-256","content":"03ce8efad1ea64b30d3b8c3a659e0595540469d728aa4c94ef61c2e702784655"}],"purl":"pkg:golang/github.com/mmcloughlin/addchain@v0.4.0","type":"library","bom-ref":"pkg:golang/github.com/mmcloughlin/addchain@v0.4.0"},{"group":"","name":"github.com/mtibben/percent","version":"v0.2.1","hashes":[{"alg":"SHA-256","content":"286f6e3be499914a7e564447b02758415dd7499aeb4a94773bd89b3414d9ae7b"}],"purl":"pkg:golang/github.com/mtibben/percent@v0.2.1","type":"library","bom-ref":"pkg:golang/github.com/mtibben/percent@v0.2.1"},{"group":"","name":"github.com/oasisprotocol/curve25519-voi","version":"v0.0.0-20230904125328-1f23a7beb09a","hashes":[{"alg":"SHA-256","content":"855a0747611511288808431b835dfb7ad37f2f1fa54ab1cf4c3dfd67fb84fb6b"}],"purl":"pkg:golang/github.com/oasisprotocol/curve25519-voi@v0.0.0-20230904125328-1f23a7beb09a","type":"library","bom-ref":"pkg:golang/github.com/oasisprotocol/curve25519-voi@v0.0.0-20230904125328-1f23a7beb09a"},{"group":"","name":"github.com/oklog/run","version":"v1.1.0","hashes":[{"alg":"SHA-256","content":"b153dd9d3653d7363000978232ed938784f6d6903714f39045f5a342593b0d55"}],"purl":"pkg:golang/github.com/oklog/run@v1.1.0","type":"library","bom-ref":"pkg:golang/github.com/oklog/run@v1.1.0"},{"group":"","name":"github.com/pelletier/go-toml/v2","version":"v2.1.0","hashes":[{"alg":"SHA-256","content":"b495366776645f09f16b80cf3bcf7d6ecc88a32c22cdd52fc9a799bab9cf3c37"}],"purl":"pkg:golang/github.com/pelletier/go-toml/v2@v2.1.0","type":"library","bom-ref":"pkg:golang/github.com/pelletier/go-toml/v2@v2.1.0"},{"group":"","name":"github.com/petermattis/goid","version":"v0.0.0-20230904192822-1876fd5063bc","hashes":[{"alg":"SHA-256","content":"a7132dc3b732530e81d9b447d190403523e0f80a12b9dd48d62c891c8ebd8c7e"}],"purl":"pkg:golang/github.com/petermattis/goid@v0.0.0-20230904192822-1876fd5063bc","type":"library","bom-ref":"pkg:golang/github.com/petermattis/goid@v0.0.0-20230904192822-1876fd5063bc"},{"group":"","name":"github.com/pkg/errors","version":"v0.9.1","hashes":[{"alg":"SHA-256","content":"6f06b0c5f1c114d57e2f6854a75ac7003b9f57720cb670d175fd6be4d20d125d"}],"purl":"pkg:golang/github.com/pkg/errors@v0.9.1","type":"library","bom-ref":"pkg:golang/github.com/pkg/errors@v0.9.1"},{"group":"","name":"github.com/pmezard/go-difflib","version":"v1.0.1-0.20181226105442-5d4384ee4fb2","hashes":[{"alg":"SHA-256","content":"88a1fbee4a05858c532b5a5c46790a92a7d3a20b1b83b819355638b110d867fe"}],"purl":"pkg:golang/github.com/pmezard/go-difflib@v1.0.1-0.20181226105442-5d4384ee4fb2","type":"library","bom-ref":"pkg:golang/github.com/pmezard/go-difflib@v1.0.1-0.20181226105442-5d4384ee4fb2"},{"group":"","name":"github.com/prometheus/client_model","version":"v0.6.0","hashes":[{"alg":"SHA-256","content":"3534079e6c45a68b8e0f40e9bcfe17ba35f709d3801903e86868724dc865cadf"}],"purl":"pkg:golang/github.com/prometheus/client_model@v0.6.0","type":"library","bom-ref":"pkg:golang/github.com/prometheus/client_model@v0.6.0"},{"group":"","name":"github.com/prometheus/common","version":"v0.47.0","hashes":[{"alg":"SHA-256","content":"d3f2acbe52047cf40243923688d48058a3d9ce2342bd1b39102e882c34e500f7"}],"purl":"pkg:golang/github.com/prometheus/common@v0.47.0","type":"library","bom-ref":"pkg:golang/github.com/prometheus/common@v0.47.0"},{"group":"","name":"github.com/prometheus/procfs","version":"v0.13.0","hashes":[{"alg":"SHA-256","content":"71de0f142479e102e718a3da28603a97e71fb8d5ed86de3764a63ab68c346358"}],"purl":"pkg:golang/github.com/prometheus/procfs@v0.13.0","type":"library","bom-ref":"pkg:golang/github.com/prometheus/procfs@v0.13.0"},{"group":"","name":"github.com/rcrowley/go-metrics","version":"v0.0.0-20201227073835-cf1acfcdf475","hashes":[{"alg":"SHA-256","content":"6c2aa7573424671306e2cf271b0899e65dd0502caaa68f58fbf64c67d56365ee"}],"purl":"pkg:golang/github.com/rcrowley/go-metrics@v0.0.0-20201227073835-cf1acfcdf475","type":"library","bom-ref":"pkg:golang/github.com/rcrowley/go-metrics@v0.0.0-20201227073835-cf1acfcdf475"},{"group":"","name":"github.com/rogpeppe/go-internal","version":"v1.12.0","hashes":[{"alg":"SHA-256","content":"13e458b9319a28a765a007ccd36c736f4156dcf69af7dc9e773615fa4ab8b9fe"}],"purl":"pkg:golang/github.com/rogpeppe/go-internal@v1.12.0","type":"library","bom-ref":"pkg:golang/github.com/rogpeppe/go-internal@v1.12.0"},{"group":"","name":"github.com/rs/cors","version":"v1.8.3","hashes":[{"alg":"SHA-256","content":"5f2aab713a79ce35abd70b09f0f21166cb19f1bfd631c31fef50c99e2b7810c5"}],"purl":"pkg:golang/github.com/rs/cors@v1.8.3","type":"library","bom-ref":"pkg:golang/github.com/rs/cors@v1.8.3"},{"group":"","name":"github.com/rs/zerolog","version":"v1.32.0","hashes":[{"alg":"SHA-256","content":"ffb98de03e6c2b024b650d9bff39e98c2dff190598ff16835d433490a5911ecb"}],"purl":"pkg:golang/github.com/rs/zerolog@v1.32.0","type":"library","bom-ref":"pkg:golang/github.com/rs/zerolog@v1.32.0"},{"group":"","name":"github.com/sagikazarmark/locafero","version":"v0.4.0","hashes":[{"alg":"SHA-256","content":"3ded56e9494f61493ffb073fe8a1616ce4427eace0604a604373b97cfb8bdc7e"}],"purl":"pkg:golang/github.com/sagikazarmark/locafero@v0.4.0","type":"library","bom-ref":"pkg:golang/github.com/sagikazarmark/locafero@v0.4.0"},{"group":"","name":"github.com/sagikazarmark/slog-shim","version":"v0.1.0","hashes":[{"alg":"SHA-256","content":"4ab712aeaf1a2adcaea84235baf4c34cad5aace59121ccd046ff86548d4091e4"}],"purl":"pkg:golang/github.com/sagikazarmark/slog-shim@v0.1.0","type":"library","bom-ref":"pkg:golang/github.com/sagikazarmark/slog-shim@v0.1.0"},{"group":"","name":"github.com/sasha-s/go-deadlock","version":"v0.3.1","hashes":[{"alg":"SHA-256","content":"17bde5f9cafcd984a1d741b1c9123aa9988280aeb855a663c1eb207d0d7f88b3"}],"purl":"pkg:golang/github.com/sasha-s/go-deadlock@v0.3.1","type":"library","bom-ref":"pkg:golang/github.com/sasha-s/go-deadlock@v0.3.1"},{"group":"","name":"github.com/sourcegraph/conc","version":"v0.3.0","hashes":[{"alg":"SHA-256","content":"49da338bb2c429b14fa985f6fc9fa204033a1e9a922d30124082aa0e617b32dd"}],"purl":"pkg:golang/github.com/sourcegraph/conc@v0.3.0","type":"library","bom-ref":"pkg:golang/github.com/sourcegraph/conc@v0.3.0"},{"group":"","name":"github.com/spf13/afero","version":"v1.11.0","hashes":[{"alg":"SHA-256","content":"187f58de921ec607f5313216b4d1b2a200393304480d7194afe85b58da018e46"}],"purl":"pkg:golang/github.com/spf13/afero@v1.11.0","type":"library","bom-ref":"pkg:golang/github.com/spf13/afero@v1.11.0"},{"group":"","name":"github.com/spf13/cast","version":"v1.6.0","hashes":[{"alg":"SHA-256","content":"6a7704a41c70243383496fd41b8ac3ac0aa22a896a34d8760d7de693ce9c01da"}],"purl":"pkg:golang/github.com/spf13/cast@v1.6.0","type":"library","bom-ref":"pkg:golang/github.com/spf13/cast@v1.6.0"},{"group":"","name":"github.com/spf13/pflag","version":"v1.0.5","hashes":[{"alg":"SHA-256","content":"31c5df227251af3e026575593812dbd1b4d9a844e488084cf48c34cb7027d818"}],"purl":"pkg:golang/github.com/spf13/pflag@v1.0.5","type":"library","bom-ref":"pkg:golang/github.com/spf13/pflag@v1.0.5"},{"group":"","name":"github.com/subosito/gotenv","version":"v1.6.0","hashes":[{"alg":"SHA-256","content":"0e4e103f97365b789bcda8c6717a4dada0dfab622b863308bcc4963ca2a8d055"}],"purl":"pkg:golang/github.com/subosito/gotenv@v1.6.0","type":"library","bom-ref":"pkg:golang/github.com/subosito/gotenv@v1.6.0"},{"group":"","name":"github.com/supranational/blst","version":"v0.3.11","hashes":[{"alg":"SHA-256","content":"8d926d7e382e76d365e1e9f5b73c0f215dca8d49d052f1b7fe3fb0f9f5689cbc"}],"purl":"pkg:golang/github.com/supranational/blst@v0.3.11","type":"library","bom-ref":"pkg:golang/github.com/supranational/blst@v0.3.11"},{"group":"","name":"github.com/syndtr/goleveldb","version":"v1.0.1-0.20220721030215-126854af5e6d","hashes":[{"alg":"SHA-256","content":"45109825b2300f98e6a8f23d5e800547439c0f1a9472d965eb3523ffe0784b8f"}],"purl":"pkg:golang/github.com/syndtr/goleveldb@v1.0.1-0.20220721030215-126854af5e6d","type":"library","bom-ref":"pkg:golang/github.com/syndtr/goleveldb@v1.0.1-0.20220721030215-126854af5e6d"},{"group":"","name":"github.com/tendermint/go-amino","version":"v0.16.0","hashes":[{"alg":"SHA-256","content":"4d05343358bf226028fad629662ef7014dd5fdd29e0a8302f52a617b667018c1"}],"purl":"pkg:golang/github.com/tendermint/go-amino@v0.16.0","type":"library","bom-ref":"pkg:golang/github.com/tendermint/go-amino@v0.16.0"},{"group":"","name":"github.com/tidwall/btree","version":"v1.7.0","hashes":[{"alg":"SHA-256","content":"b700fd5d10398e3f555101842f30cee073d04cd26ca1659f6042fe11443670a6"}],"purl":"pkg:golang/github.com/tidwall/btree@v1.7.0","type":"library","bom-ref":"pkg:golang/github.com/tidwall/btree@v1.7.0"},{"group":"","name":"github.com/ulikunitz/xz","version":"v0.5.11","hashes":[{"alg":"SHA-256","content":"9dbcfa93ba9b3e61f8211aa67cea65430fed6e54a0a93a81c31918d285adff5e"}],"purl":"pkg:golang/github.com/ulikunitz/xz@v0.5.11","type":"library","bom-ref":"pkg:golang/github.com/ulikunitz/xz@v0.5.11"},{"group":"","name":"github.com/zondax/hid","version":"v0.9.2","hashes":[{"alg":"SHA-256","content":"979c2db5c3f48f0b5d2e3aa330c58554413b775cced23bd23c0f4e3d9c56a443"}],"purl":"pkg:golang/github.com/zondax/hid@v0.9.2","type":"library","bom-ref":"pkg:golang/github.com/zondax/hid@v0.9.2"},{"group":"","name":"github.com/zondax/ledger-go","version":"v0.14.3","hashes":[{"alg":"SHA-256","content":"20a29aa31ba9b81e3783837179099b2d7bfb4fd02543289ed54a476f7e36c9c2"}],"purl":"pkg:golang/github.com/zondax/ledger-go@v0.14.3","type":"library","bom-ref":"pkg:golang/github.com/zondax/ledger-go@v0.14.3"},{"group":"","name":"go.etcd.io/bbolt","version":"v1.3.8","hashes":[{"alg":"SHA-256","content":"37d324c3d5fcc797eea72d082ac9aea95b68183cb1b1a0e56e4e11774e48010c"}],"purl":"pkg:golang/go.etcd.io/bbolt@v1.3.8","type":"library","bom-ref":"pkg:golang/go.etcd.io/bbolt@v1.3.8"},{"group":"","name":"go.opencensus.io","version":"v0.24.0","hashes":[{"alg":"SHA-256","content":"bcd2bc1bda7b6808af91b9a8adfe2ffbb1e0c7e66cd3263ed1f3ad8017e340aa"}],"licenses":[{"license":{"id":"Apache-2.0"}}],"purl":"pkg:golang/go.opencensus.io@v0.24.0","type":"library","bom-ref":"pkg:golang/go.opencensus.io@v0.24.0"},{"group":"","name":"go.opentelemetry.io/contrib/instrumentation/google.golang.org/grpc/otelgrpc","version":"v0.47.0","hashes":[{"alg":"SHA-256","content":"afdbd6b0f4bfdc0408b6fdce4a5109fc4e266eb8546dbc35f2678e8c0acfb4a4"}],"purl":"pkg:golang/go.opentelemetry.io/contrib/instrumentation/google.golang.org/grpc/otelgrpc@v0.47.0","type":"library","bom-ref":"pkg:golang/go.opentelemetry.io/contrib/instrumentation/google.golang.org/grpc/otelgrpc@v0.47.0"},{"group":"","name":"go.opentelemetry.io/contrib/instrumentation/net/http/otelhttp","version":"v0.47.0","hashes":[{"alg":"SHA-256","content":"48ad942fbdd9cb5aaebd13e89e63a64438969352815772f221e788c5c100a56c"}],"purl":"pkg:golang/go.opentelemetry.io/contrib/instrumentation/net/http/otelhttp@v0.47.0","type":"library","bom-ref":"pkg:golang/go.opentelemetry.io/contrib/instrumentation/net/http/otelhttp@v0.47.0"},{"group":"","name":"go.opentelemetry.io/otel","version":"v1.22.0","hashes":[{"alg":"SHA-256","content":"7a85788808b711af0b900108f7e1854f8e0ee93fc3d06580545c995420baa4c2"}],"purl":"pkg:golang/go.opentelemetry.io/otel@v1.22.0","type":"library","bom-ref":"pkg:golang/go.opentelemetry.io/otel@v1.22.0"},{"group":"","name":"go.opentelemetry.io/otel/metric","version":"v1.22.0","hashes":[{"alg":"SHA-256","content":"7af2468d5a59bf4990e50051268045eb8c8cb8e7f8c4259d5e32bca7316f9626"}],"purl":"pkg:golang/go.opentelemetry.io/otel/metric@v1.22.0","type":"library","bom-ref":"pkg:golang/go.opentelemetry.io/otel/metric@v1.22.0"},{"group":"","name":"go.opentelemetry.io/otel/trace","version":"v1.22.0","hashes":[{"alg":"SHA-256","content":"45b6c75d5a8a112f5087366afdf13952739220ba91b78d1adb5b0fc361ded71a"}],"purl":"pkg:golang/go.opentelemetry.io/otel/trace@v1.22.0","type":"library","bom-ref":"pkg:golang/go.opentelemetry.io/otel/trace@v1.22.0"},{"group":"","name":"golang.org/x/crypto","version":"v0.21.0","hashes":[{"alg":"SHA-256","content":"d013fb62f555f6005b54ac9e4c6d06ca7fa0666f786e26ce5b90630c460038cb"}],"purl":"pkg:golang/golang.org/x/crypto@v0.21.0","type":"library","bom-ref":"pkg:golang/golang.org/x/crypto@v0.21.0"},{"group":"","name":"golang.org/x/exp","version":"v0.0.0-20240314144324-c7f7c6466f7f","hashes":[{"alg":"SHA-256","content":"0b1985bd3048348db83bf8fc898ec7d711f3c768b83acca0b8d06637fb8fb6a7"}],"purl":"pkg:golang/golang.org/x/exp@v0.0.0-20240314144324-c7f7c6466f7f","type":"library","bom-ref":"pkg:golang/golang.org/x/exp@v0.0.0-20240314144324-c7f7c6466f7f"},{"group":"","name":"golang.org/x/net","version":"v0.23.0","hashes":[{"alg":"SHA-256","content":"24a82158a28e49d270a56d86131d096bb7e668a9ccb1bbbe3165594e89126268"}],"purl":"pkg:golang/golang.org/x/net@v0.23.0","type":"library","bom-ref":"pkg:golang/golang.org/x/net@v0.23.0"},{"group":"","name":"golang.org/x/oauth2","version":"v0.18.0","hashes":[{"alg":"SHA-256","content":"59fee49f01b430fa1620c30180594469250368ab24a747427eb9494495db062f"}],"purl":"pkg:golang/golang.org/x/oauth2@v0.18.0","type":"library","bom-ref":"pkg:golang/golang.org/x/oauth2@v0.18.0"},{"group":"","name":"golang.org/x/sys","version":"v0.18.0","hashes":[{"alg":"SHA-256","content":"fd55217a989a24c414a78fa86bfed9af50f6de66ba5532c862338e4c564f51c0"}],"purl":"pkg:golang/golang.org/x/sys@v0.18.0","type":"library","bom-ref":"pkg:golang/golang.org/x/sys@v0.18.0"},{"group":"","name":"golang.org/x/term","version":"v0.18.0","hashes":[{"alg":"SHA-256","content":"20bc0049e92d0373a746feda999d71844fca4d1faee74a5b5df674dfee8dc79f"}],"purl":"pkg:golang/golang.org/x/term@v0.18.0","type":"library","bom-ref":"pkg:golang/golang.org/x/term@v0.18.0"},{"group":"","name":"golang.org/x/time","version":"v0.5.0","hashes":[{"alg":"SHA-256","content":"dc1a73281cbfb2136156e718fcc58ecb1d74b45dd2161f5074bbb16d5cac3d03"}],"purl":"pkg:golang/golang.org/x/time@v0.5.0","type":"library","bom-ref":"pkg:golang/golang.org/x/time@v0.5.0"},{"group":"","name":"google.golang.org/api","version":"v0.162.0","hashes":[{"alg":"SHA-256","content":"e92ba50e47e8048838345982b99dfd5de7808121c23de71f494b83c989401ecd"}],"purl":"pkg:golang/google.golang.org/api@v0.162.0","type":"library","bom-ref":"pkg:golang/google.golang.org/api@v0.162.0"},{"group":"","name":"google.golang.org/appengine","version":"v1.6.8","hashes":[{"alg":"SHA-256","content":"d632778c102b161e697205bc802b512677a95bc1730f5578e0525f7cb8b3fc3b"}],"purl":"pkg:golang/google.golang.org/appengine@v1.6.8","type":"library","bom-ref":"pkg:golang/google.golang.org/appengine@v1.6.8"},{"group":"","name":"google.golang.org/genproto","version":"v0.0.0-20240213162025-012b6fc9bca9","hashes":[{"alg":"SHA-256","content":"9aa1db548a78f0cba1ed8c2cb3f003e88e6435529932601afd0116e7c1b1a76b"}],"purl":"pkg:golang/google.golang.org/genproto@v0.0.0-20240213162025-012b6fc9bca9","type":"library","bom-ref":"pkg:golang/google.golang.org/genproto@v0.0.0-20240213162025-012b6fc9bca9"},{"group":"","name":"google.golang.org/genproto/googleapis/api","version":"v0.0.0-20240205150955-31a09d347014","hashes":[{"alg":"SHA-256","content":"adb1cc4840f2a185fada74552ce09ce10b751dbb1dcad018a15c208e23a11772"}],"purl":"pkg:golang/google.golang.org/genproto/googleapis/api@v0.0.0-20240205150955-31a09d347014","type":"library","bom-ref":"pkg:golang/google.golang.org/genproto/googleapis/api@v0.0.0-20240205150955-31a09d347014"},{"group":"","name":"google.golang.org/genproto/googleapis/rpc","version":"v0.0.0-20240221002015-b0ce06bbee7c","hashes":[{"alg":"SHA-256","content":"1f83b5ecc03f3c4f41b06c77c3e6be5b654e2cb0f541fee8267780a14e9692d6"}],"purl":"pkg:golang/google.golang.org/genproto/googleapis/rpc@v0.0.0-20240221002015-b0ce06bbee7c","type":"library","bom-ref":"pkg:golang/google.golang.org/genproto/googleapis/rpc@v0.0.0-20240221002015-b0ce06bbee7c"},{"group":"","name":"google.golang.org/protobuf","version":"v1.33.0","hashes":[{"alg":"SHA-256","content":"73a3fa1975fab076eafc6a55e8c19911dc2158f7180609e100784a6dc518a68b"}],"purl":"pkg:golang/google.golang.org/protobuf@v1.33.0","type":"library","bom-ref":"pkg:golang/google.golang.org/protobuf@v1.33.0"},{"group":"","name":"gopkg.in/ini.v1","version":"v1.67.0","hashes":[{"alg":"SHA-256","content":"a4d2dff16522c8d12d423baee46e6f4e6d3a4c4bfdb6c220780bcaf213ab3f89"}],"purl":"pkg:golang/gopkg.in/ini.v1@v1.67.0","type":"library","bom-ref":"pkg:golang/gopkg.in/ini.v1@v1.67.0"},{"group":"","name":"gotest.tools/v3","version":"v3.5.1","hashes":[{"alg":"SHA-256","content":"8accb758acfb18aeae370fec6c7cdf2812ef96f5f0532574ea7e9baccc71a295"}],"purl":"pkg:golang/gotest.tools/v3@v3.5.1","type":"library","bom-ref":"pkg:golang/gotest.tools/v3@v3.5.1"},{"group":"","name":"nhooyr.io/websocket","version":"v1.8.6","hashes":[{"alg":"SHA-256","content":"07bd0364ff086a423ae51550e7532c58fffc8e774d99adba0d503f9c5482816d"}],"purl":"pkg:golang/nhooyr.io/websocket@v1.8.6","type":"library","bom-ref":"pkg:golang/nhooyr.io/websocket@v1.8.6"},{"group":"","name":"pgregory.net/rapid","version":"v1.1.0","hashes":[{"alg":"SHA-256","content":"3d8e579431a3d3e575142ab4a35f7615d461a4a1c64d1216060aa30c14ebab4e"}],"purl":"pkg:golang/pgregory.net/rapid@v1.1.0","type":"library","bom-ref":"pkg:golang/pgregory.net/rapid@v1.1.0"},{"group":"","name":"rsc.io/tmplfunc","version":"v0.0.3","hashes":[{"alg":"SHA-256","content":"006dec4cfcc495bd48a37620e2fa15f4019926e95e180c1a551c4bf4ce3d3e10"}],"purl":"pkg:golang/rsc.io/tmplfunc@v0.0.3","type":"library","bom-ref":"pkg:golang/rsc.io/tmplfunc@v0.0.3"},{"group":"","name":"sigs.k8s.io/yaml","version":"v1.4.0","hashes":[{"alg":"SHA-256","content":"12397bfee4f3ecf480e1e28cc900944e785960d98b225fb97369503c647604f6"}],"purl":"pkg:golang/sigs.k8s.io/yaml@v1.4.0","type":"library","bom-ref":"pkg:golang/sigs.k8s.io/yaml@v1.4.0"},{"group":"","name":"cosmossdk.io/simapp","version":"v0.0.0-20230224204036-a6adb0821462","hashes":[{"alg":"SHA-256","content":"e0377734ba0b62837dd24674bb21e84c7cd5564f7e274bf81e165104d4c0ab67"}],"purl":"pkg:golang/cosmossdk.io/simapp@v0.0.0-20230224204036-a6adb0821462","type":"library","bom-ref":"pkg:golang/cosmossdk.io/simapp@v0.0.0-20230224204036-a6adb0821462"},{"group":"","name":"github.com/cosmos/gogoproto","version":"v1.4.12","hashes":[{"alg":"SHA-256","content":"2e76686f56d745d528a8c32dc1895c477c23884966942f8592369946fd7f78b6"}],"purl":"pkg:golang/github.com/cosmos/gogoproto@v1.4.12","type":"library","bom-ref":"pkg:golang/github.com/cosmos/gogoproto@v1.4.12"},{"group":"","name":"github.com/docker/docker","version":"v24.0.9+incompatible","hashes":[{"alg":"SHA-256","content":"784281d0dd2be4d5ff235904bde133d396dcbbcb4b0bff1acc966cbe2ba9f129"}],"purl":"pkg:golang/github.com/docker/docker@v24.0.9%2Bincompatible","type":"library","bom-ref":"pkg:golang/github.com/docker/docker@v24.0.9+incompatible"},{"group":"","name":"github.com/icza/dyno","version":"v0.0.0-20220812133438-f0b6f8a18845","hashes":[{"alg":"SHA-256","content":"735b512ace53c7b136fae1c64b2ca77338858ef1a982fe07d87aea5de510fd49"}],"purl":"pkg:golang/github.com/icza/dyno@v0.0.0-20220812133438-f0b6f8a18845","type":"library","bom-ref":"pkg:golang/github.com/icza/dyno@v0.0.0-20220812133438-f0b6f8a18845"},{"group":"","name":"github.com/moby/moby","version":"v24.0.9+incompatible","hashes":[{"alg":"SHA-256","content":"7c35d543af92df8d2f7903efdf90b30da8460661ec89c945c1f132801fd358c7"}],"purl":"pkg:golang/github.com/moby/moby@v24.0.9%2Bincompatible","type":"library","bom-ref":"pkg:golang/github.com/moby/moby@v24.0.9+incompatible"},{"group":"","name":"github.com/strangelove-ventures/interchaintest/v8","version":"v8.0.1-0.20231114192524-e3719592933b","hashes":[{"alg":"SHA-256","content":"4db55a05349af58eff263fc97aaa07efd7c07324221e5a33d73c57c4a8ed0850"}],"purl":"pkg:golang/github.com/strangelove-ventures/interchaintest/v8@v8.0.1-0.20231114192524-e3719592933b","type":"library","bom-ref":"pkg:golang/github.com/strangelove-ventures/interchaintest/v8@v8.0.1-0.20231114192524-e3719592933b"},{"group":"","name":"go.uber.org/zap","version":"v1.27.0","hashes":[{"alg":"SHA-256","content":"181daa14b33b71353cecc5913f698f223a9f2039c6bbe5483b857f49d846a361"}],"purl":"pkg:golang/go.uber.org/zap@v1.27.0","type":"library","bom-ref":"pkg:golang/go.uber.org/zap@v1.27.0"},{"group":"","name":"cosmossdk.io/client/v2","version":"v2.0.0-beta.1","hashes":[{"alg":"SHA-256","content":"244512bbd9a8359438914de2af50ca0f9794e1b9659807b1ac65a399bf64f2a5"}],"purl":"pkg:golang/cosmossdk.io/client/v2@v2.0.0-beta.1","type":"library","bom-ref":"pkg:golang/cosmossdk.io/client/v2@v2.0.0-beta.1"},{"group":"","name":"cosmossdk.io/x/circuit","version":"v0.1.0","hashes":[{"alg":"SHA-256","content":"603cdb95513cf84faeacf610ab992ae5fa1163f233857a2f4985dbe27c1ddfdc"}],"purl":"pkg:golang/cosmossdk.io/x/circuit@v0.1.0","type":"library","bom-ref":"pkg:golang/cosmossdk.io/x/circuit@v0.1.0"},{"group":"","name":"cosmossdk.io/x/evidence","version":"v0.1.0","hashes":[{"alg":"SHA-256","content":"8536a2897b28889dc89cccf5ba9b601740671aa44e96500df26c22b0e30cb1fc"}],"purl":"pkg:golang/cosmossdk.io/x/evidence@v0.1.0","type":"library","bom-ref":"pkg:golang/cosmossdk.io/x/evidence@v0.1.0"},{"group":"","name":"github.com/99designs/keyring","version":"v1.2.2","hashes":[{"alg":"SHA-256","content":"c1eb3f16b07273c8fb94538018b19234483c7ff3da2377204c1aa11641d4acf9"}],"purl":"pkg:golang/github.com/99designs/keyring@v1.2.2","type":"library","bom-ref":"pkg:golang/github.com/99designs/keyring@v1.2.2"},{"group":"","name":"github.com/BurntSushi/toml","version":"v1.3.2","hashes":[{"alg":"SHA-256","content":"0b15d820dac2f2a22212716b3b109aec9cb90451e55e7514da96e2704bb26f14"}],"purl":"pkg:golang/github.com/BurntSushi/toml@v1.3.2","type":"library","bom-ref":"pkg:golang/github.com/BurntSushi/toml@v1.3.2"},{"group":"","name":"github.com/ChainSafe/go-schnorrkel","version":"v1.0.0","hashes":[{"alg":"SHA-256","content":"769cc7615c4b65ca7ca63955f8ef9447c2b41e9ff3eef71c84149b3011210b0e"}],"purl":"pkg:golang/github.com/ChainSafe/go-schnorrkel@v1.0.0","type":"library","bom-ref":"pkg:golang/github.com/ChainSafe/go-schnorrkel@v1.0.0"},{"group":"","name":"github.com/ComposableFi/go-subkey/v2","version":"v2.0.0-tm03420","hashes":[{"alg":"SHA-256","content":"298922317e406ce9575d87f192b60fad13d5e846d55002d3421e69b54389ceef"}],"purl":"pkg:golang/github.com/ComposableFi/go-subkey/v2@v2.0.0-tm03420","type":"library","bom-ref":"pkg:golang/github.com/ComposableFi/go-subkey/v2@v2.0.0-tm03420"},{"group":"","name":"github.com/FactomProject/basen","version":"v0.0.0-20150613233007-fe3947df716e","hashes":[{"alg":"SHA-256","content":"90652a84777ffe6bac7484d68c5bcd4c79fdd161bd6cc2c110f419d7b0a6969c"}],"purl":"pkg:golang/github.com/FactomProject/basen@v0.0.0-20150613233007-fe3947df716e","type":"library","bom-ref":"pkg:golang/github.com/FactomProject/basen@v0.0.0-20150613233007-fe3947df716e"},{"group":"","name":"github.com/FactomProject/btcutilecc","version":"v0.0.0-20130527213604-d3a63a5752ec","hashes":[{"alg":"SHA-256","content":"083f1496794b0e2a9bdfa2f5d74baa88fda249f9558f1f60ff753d842238ab65"}],"purl":"pkg:golang/github.com/FactomProject/btcutilecc@v0.0.0-20130527213604-d3a63a5752ec","type":"library","bom-ref":"pkg:golang/github.com/FactomProject/btcutilecc@v0.0.0-20130527213604-d3a63a5752ec"},{"group":"","name":"github.com/Microsoft/go-winio","version":"v0.6.1","hashes":[{"alg":"SHA-256","content":"2d174aa4529f7686e59fc526ba261c28fa2df43dafeacbcde7eb001fee248d43"}],"purl":"pkg:golang/github.com/Microsoft/go-winio@v0.6.1","type":"library","bom-ref":"pkg:golang/github.com/Microsoft/go-winio@v0.6.1"},{"group":"","name":"github.com/OneOfOne/xxhash","version":"v1.2.8","hashes":[{"alg":"SHA-256","content":"7996e1c9a0180f8d521924ac9e6729c55a11890fcc3d44e351d208393f549bb4"}],"purl":"pkg:golang/github.com/OneOfOne/xxhash@v1.2.8","type":"library","bom-ref":"pkg:golang/github.com/OneOfOne/xxhash@v1.2.8"},{"group":"","name":"github.com/StirlingMarketingGroup/go-namecase","version":"v1.0.0","hashes":[{"alg":"SHA-256","content":"66ca1229c69f700cee071fac9dd6f11eefd18c37034eb11d4f852f8678877e2a"}],"purl":"pkg:golang/github.com/StirlingMarketingGroup/go-namecase@v1.0.0","type":"library","bom-ref":"pkg:golang/github.com/StirlingMarketingGroup/go-namecase@v1.0.0"},{"group":"","name":"github.com/cenkalti/backoff/v4","version":"v4.2.1","hashes":[{"alg":"SHA-256","content":"63754d9ed90e50fc5355e53127f1b9bdc33ffc09707e6c98a3355ca2684b8991"}],"purl":"pkg:golang/github.com/cenkalti/backoff/v4@v4.2.1","type":"library","bom-ref":"pkg:golang/github.com/cenkalti/backoff/v4@v4.2.1"},{"group":"","name":"github.com/cockroachdb/apd/v2","version":"v2.0.2","hashes":[{"alg":"SHA-256","content":"0c3c519730b6968dffbd29664a84bb264a9b6eb0113ee14e1abd01f69bcddc6c"}],"purl":"pkg:golang/github.com/cockroachdb/apd/v2@v2.0.2","type":"library","bom-ref":"pkg:golang/github.com/cockroachdb/apd/v2@v2.0.2"},{"group":"","name":"github.com/containerd/containerd","version":"v1.7.11","hashes":[{"alg":"SHA-256","content":"e5496e1f11d35f6addbd8b99e4e2530b99bf28936cd19b3dc15a099bdcdfe591"}],"purl":"pkg:golang/github.com/containerd/containerd@v1.7.11","type":"library","bom-ref":"pkg:golang/github.com/containerd/containerd@v1.7.11"},{"group":"","name":"github.com/deckarep/golang-set","version":"v1.8.0","hashes":[{"alg":"SHA-256","content":"e6723cecac04ef082c054d45e06280c3642877ba799324b7f37acfebea3aaaaa"}],"purl":"pkg:golang/github.com/deckarep/golang-set@v1.8.0","type":"library","bom-ref":"pkg:golang/github.com/deckarep/golang-set@v1.8.0"},{"group":"","name":"github.com/decred/base58","version":"v1.0.4","hashes":[{"alg":"SHA-256","content":"8c9b3028f11dbe9169bdfeddb03bc56722d3db6c59f655aa101c97dfca0677d1"}],"purl":"pkg:golang/github.com/decred/base58@v1.0.4","type":"library","bom-ref":"pkg:golang/github.com/decred/base58@v1.0.4"},{"group":"","name":"github.com/decred/dcrd/crypto/blake256","version":"v1.0.1","hashes":[{"alg":"SHA-256","content":"d8e7e0359e700e972c1661e608ae606533dc097aa59b602bcd4224c3d733349a"}],"purl":"pkg:golang/github.com/decred/dcrd/crypto/blake256@v1.0.1","type":"library","bom-ref":"pkg:golang/github.com/decred/dcrd/crypto/blake256@v1.0.1"},{"group":"","name":"github.com/decred/dcrd/dcrec/secp256k1/v2","version":"v2.0.1","hashes":[{"alg":"SHA-256","content":"5e6cb391a5c1cbb66f1ddad30255c08e9a20f2a2920166b7cdeef2ab35a68267"}],"purl":"pkg:golang/github.com/decred/dcrd/dcrec/secp256k1/v2@v2.0.1","type":"library","bom-ref":"pkg:golang/github.com/decred/dcrd/dcrec/secp256k1/v2@v2.0.1"},{"group":"","name":"github.com/docker/distribution","version":"v2.8.2+incompatible","hashes":[{"alg":"SHA-256","content":"276813dae76c0c037de948f829f70c46a634ff2a51fa8c985189a36bc1fecbec"}],"purl":"pkg:golang/github.com/docker/distribution@v2.8.2%2Bincompatible","type":"library","bom-ref":"pkg:golang/github.com/docker/distribution@v2.8.2+incompatible"},{"group":"","name":"github.com/docker/go-connections","version":"v0.4.0","hashes":[{"alg":"SHA-256","content":"19b77b20ea291e347c229874dedb158aee2721eb395e10efc876d3b54c6679e7"}],"purl":"pkg:golang/github.com/docker/go-connections@v0.4.0","type":"library","bom-ref":"pkg:golang/github.com/docker/go-connections@v0.4.0"},{"group":"","name":"github.com/docker/go-units","version":"v0.5.0","hashes":[{"alg":"SHA-256","content":"7e03e14d474ef83fc993ce910cb969b69897433807245ee0c9d0c36da20ae039"}],"purl":"pkg:golang/github.com/docker/go-units@v0.5.0","type":"library","bom-ref":"pkg:golang/github.com/docker/go-units@v0.5.0"},{"group":"","name":"github.com/gtank/merlin","version":"v0.1.1","hashes":[{"alg":"SHA-256","content":"4fce9d9d82617063a1e418d91422564c37932bb5d6f2e13e136d42cbf6c843eb"}],"purl":"pkg:golang/github.com/gtank/merlin@v0.1.1","type":"library","bom-ref":"pkg:golang/github.com/gtank/merlin@v0.1.1"},{"group":"","name":"github.com/gtank/ristretto255","version":"v0.1.2","hashes":[{"alg":"SHA-256","content":"3e1e4ea4ee9cef12941913997d654b8897fd89c303c14788bd8e0e9a5616ebda"}],"purl":"pkg:golang/github.com/gtank/ristretto255@v0.1.2","type":"library","bom-ref":"pkg:golang/github.com/gtank/ristretto255@v0.1.2"},{"group":"","name":"github.com/ipfs/go-cid","version":"v0.4.1","hashes":[{"alg":"SHA-256","content":"b901f00de5f873a0adcab17076aca1a4d73155ec2eaf533b97b7cd53b2cac199"}],"purl":"pkg:golang/github.com/ipfs/go-cid@v0.4.1","type":"library","bom-ref":"pkg:golang/github.com/ipfs/go-cid@v0.4.1"},{"group":"","name":"github.com/kballard/go-shellquote","version":"v0.0.0-20180428030007-95032a82bc51","hashes":[{"alg":"SHA-256","content":"0b31845a3edc620b1d1fc7408c1184af9f01a04ed272e2ddf9fc05678e3eff1f"}],"purl":"pkg:golang/github.com/kballard/go-shellquote@v0.0.0-20180428030007-95032a82bc51","type":"library","bom-ref":"pkg:golang/github.com/kballard/go-shellquote@v0.0.0-20180428030007-95032a82bc51"},{"group":"","name":"github.com/klauspost/cpuid/v2","version":"v2.2.5","hashes":[{"alg":"SHA-256","content":"2dccfc9817405492015737b0b5c2e870ad7697763e272b5962968cae8a43530b"}],"purl":"pkg:golang/github.com/klauspost/cpuid/v2@v2.2.5","type":"library","bom-ref":"pkg:golang/github.com/klauspost/cpuid/v2@v2.2.5"},{"group":"","name":"github.com/libp2p/go-libp2p","version":"v0.31.0","hashes":[{"alg":"SHA-256","content":"5bf1442b573fb74e0f6d11f77c0f62e68b9cbb961c82b1b4255a01593d41ec48"}],"purl":"pkg:golang/github.com/libp2p/go-libp2p@v0.31.0","type":"library","bom-ref":"pkg:golang/github.com/libp2p/go-libp2p@v0.31.0"},{"group":"","name":"github.com/mimoo/StrobeGo","version":"v0.0.0-20220103164710-9a04d6ca976b","hashes":[{"alg":"SHA-256","content":"c712dbda2a7ab1252db378358ab3d51f293f0c6b25c10b0d3a8f48eec9897cd5"}],"purl":"pkg:golang/github.com/mimoo/StrobeGo@v0.0.0-20220103164710-9a04d6ca976b","type":"library","bom-ref":"pkg:golang/github.com/mimoo/StrobeGo@v0.0.0-20220103164710-9a04d6ca976b"},{"group":"","name":"github.com/minio/sha256-simd","version":"v1.0.1","hashes":[{"alg":"SHA-256","content":"3f3e8028c8947678022e97932ff44963533dad4b8f318ba3579c498ed6d148df"}],"purl":"pkg:golang/github.com/minio/sha256-simd@v1.0.1","type":"library","bom-ref":"pkg:golang/github.com/minio/sha256-simd@v1.0.1"},{"group":"","name":"github.com/misko9/go-substrate-rpc-client/v4","version":"v4.0.0-20230913220906-b988ea7da0c2","hashes":[{"alg":"SHA-256","content":"43907139df45c49a98a78bc288b19575eb5e70f7164e651022ed1b462818a2c5"}],"purl":"pkg:golang/github.com/misko9/go-substrate-rpc-client/v4@v4.0.0-20230913220906-b988ea7da0c2","type":"library","bom-ref":"pkg:golang/github.com/misko9/go-substrate-rpc-client/v4@v4.0.0-20230913220906-b988ea7da0c2"},{"group":"","name":"github.com/moby/patternmatcher","version":"v0.5.0","hashes":[{"alg":"SHA-256","content":"8433e8c8ea4363b3abacc0cb698a18de17f9da034247f60e518c64840a492317"}],"purl":"pkg:golang/github.com/moby/patternmatcher@v0.5.0","type":"library","bom-ref":"pkg:golang/github.com/moby/patternmatcher@v0.5.0"},{"group":"","name":"github.com/moby/sys/sequential","version":"v0.5.0","hashes":[{"alg":"SHA-256","content":"b47d9c38eb3957d3253e25dc433442f9e13269beb8e0f58a19161a695e59665a"}],"purl":"pkg:golang/github.com/moby/sys/sequential@v0.5.0","type":"library","bom-ref":"pkg:golang/github.com/moby/sys/sequential@v0.5.0"},{"group":"","name":"github.com/mr-tron/base58","version":"v1.2.0","hashes":[{"alg":"SHA-256","content":"0629cc73fb109ed9481357eb4264453d4a0f035664afc551801763588da63707"}],"purl":"pkg:golang/github.com/mr-tron/base58@v1.2.0","type":"library","bom-ref":"pkg:golang/github.com/mr-tron/base58@v1.2.0"},{"group":"","name":"github.com/multiformats/go-base32","version":"v0.1.0","hashes":[{"alg":"SHA-256","content":"2a3ded158eb336bf8005832a79435e1af9080bf51882d5a26c3713d2b1319db2"}],"purl":"pkg:golang/github.com/multiformats/go-base32@v0.1.0","type":"library","bom-ref":"pkg:golang/github.com/multiformats/go-base32@v0.1.0"},{"group":"","name":"github.com/multiformats/go-base36","version":"v0.2.0","hashes":[{"alg":"SHA-256","content":"aaf9ca13efaffb631609f78f0a55048c4efc67b3f66b5515d311e059cd21929e"}],"purl":"pkg:golang/github.com/multiformats/go-base36@v0.2.0","type":"library","bom-ref":"pkg:golang/github.com/multiformats/go-base36@v0.2.0"},{"group":"","name":"github.com/multiformats/go-multiaddr","version":"v0.11.0","hashes":[{"alg":"SHA-256","content":"816526d102d1e2d850ebe645e925d4c3c623b704123daa4808cf8d9829311d23"}],"purl":"pkg:golang/github.com/multiformats/go-multiaddr@v0.11.0","type":"library","bom-ref":"pkg:golang/github.com/multiformats/go-multiaddr@v0.11.0"},{"group":"","name":"github.com/multiformats/go-multibase","version":"v0.2.0","hashes":[{"alg":"SHA-256","content":"6c50595f894a080ff6972385480a0a1f9492ea83f28ed9f32bf5d31433e436e9"}],"purl":"pkg:golang/github.com/multiformats/go-multibase@v0.2.0","type":"library","bom-ref":"pkg:golang/github.com/multiformats/go-multibase@v0.2.0"},{"group":"","name":"github.com/multiformats/go-multicodec","version":"v0.9.0","hashes":[{"alg":"SHA-256","content":"2f741342f3086950645ce5d7b5599813e2c8d7a8b5e31b9aa23aff1fb022e789"}],"purl":"pkg:golang/github.com/multiformats/go-multicodec@v0.9.0","type":"library","bom-ref":"pkg:golang/github.com/multiformats/go-multicodec@v0.9.0"},{"group":"","name":"github.com/multiformats/go-multihash","version":"v0.2.3","hashes":[{"alg":"SHA-256","content":"75780a5c25e307376c7012e4f4992320d884b0229155c87dd0c75a1a22acbd23"}],"purl":"pkg:golang/github.com/multiformats/go-multihash@v0.2.3","type":"library","bom-ref":"pkg:golang/github.com/multiformats/go-multihash@v0.2.3"},{"group":"","name":"github.com/multiformats/go-varint","version":"v0.0.7","hashes":[{"alg":"SHA-256","content":"afc3d4630fdf0ff4a304288a3a80e5185e906b03842e9640bbd7a2a12a2cfce5"}],"purl":"pkg:golang/github.com/multiformats/go-varint@v0.0.7","type":"library","bom-ref":"pkg:golang/github.com/multiformats/go-varint@v0.0.7"},{"group":"","name":"github.com/opencontainers/go-digest","version":"v1.0.0","hashes":[{"alg":"SHA-256","content":"d09ce53248f44d1cd065f26456fcdb3f41c147720acc4ae7bf604d1b85b83003"}],"purl":"pkg:golang/github.com/opencontainers/go-digest@v1.0.0","type":"library","bom-ref":"pkg:golang/github.com/opencontainers/go-digest@v1.0.0"},{"group":"","name":"github.com/opencontainers/image-spec","version":"v1.1.0-rc2.0.20221005185240-3a7f492d3f1b","hashes":[{"alg":"SHA-256","content":"dce5628e98a820a6164ea8e21b4cdf17ac2fa09e1f01719b8dd66e236360b114"}],"purl":"pkg:golang/github.com/opencontainers/image-spec@v1.1.0-rc2.0.20221005185240-3a7f492d3f1b","type":"library","bom-ref":"pkg:golang/github.com/opencontainers/image-spec@v1.1.0-rc2.0.20221005185240-3a7f492d3f1b"},{"group":"","name":"github.com/opencontainers/runc","version":"v1.1.12","hashes":[{"alg":"SHA-256","content":"4be950c127e77290616bb5d3cbfe650705a09b9fb2e4c6bf3b8e0491bcbd14af"}],"purl":"pkg:golang/github.com/opencontainers/runc@v1.1.12","type":"library","bom-ref":"pkg:golang/github.com/opencontainers/runc@v1.1.12"},{"group":"","name":"github.com/pelletier/go-toml","version":"v1.9.5","hashes":[{"alg":"SHA-256","content":"bb59d1fc43dc1127de23fb3351929db49d3144d6d4a003429283ae68ec7563e7"}],"purl":"pkg:golang/github.com/pelletier/go-toml@v1.9.5","type":"library","bom-ref":"pkg:golang/github.com/pelletier/go-toml@v1.9.5"},{"group":"","name":"github.com/pierrec/xxHash","version":"v0.1.5","hashes":[{"alg":"SHA-256","content":"c36c1a5b96686bf59ce18a9ed3082b2180062aa44c7fb7339f61cd2979ae2fe2"}],"purl":"pkg:golang/github.com/pierrec/xxHash@v0.1.5","type":"library","bom-ref":"pkg:golang/github.com/pierrec/xxHash@v0.1.5"},{"group":"","name":"github.com/remyoudompheng/bigfft","version":"v0.0.0-20230129092748-24d4a6f8daec","hashes":[{"alg":"SHA-256","content":"aaa6c7ca1f2feb40e103b0a858ae68442a8bacc1d11a8c580924bd123033e84a"}],"purl":"pkg:golang/github.com/remyoudompheng/bigfft@v0.0.0-20230129092748-24d4a6f8daec","type":"library","bom-ref":"pkg:golang/github.com/remyoudompheng/bigfft@v0.0.0-20230129092748-24d4a6f8daec"},{"group":"","name":"github.com/sirupsen/logrus","version":"v1.9.3","hashes":[{"alg":"SHA-256","content":"9da1cbb8ba0388fe231cda3d474b0204cb5619e229ae86fbe2656c213e2a6044"}],"purl":"pkg:golang/github.com/sirupsen/logrus@v1.9.3","type":"library","bom-ref":"pkg:golang/github.com/sirupsen/logrus@v1.9.3"},{"group":"","name":"github.com/spaolacci/murmur3","version":"v1.1.0","hashes":[{"alg":"SHA-256","content":"27021ab0e5b253a7fef9986212e7fcef136cce6480da6c833362b3bbd1f04140"}],"purl":"pkg:golang/github.com/spaolacci/murmur3@v1.1.0","type":"library","bom-ref":"pkg:golang/github.com/spaolacci/murmur3@v1.1.0"},{"group":"","name":"github.com/tyler-smith/go-bip32","version":"v1.0.0","hashes":[{"alg":"SHA-256","content":"a27a2df9e1e49f35780553f0af3a98e4ea15a720af9f00fb94c6b02f9690ba91"}],"purl":"pkg:golang/github.com/tyler-smith/go-bip32@v1.0.0","type":"library","bom-ref":"pkg:golang/github.com/tyler-smith/go-bip32@v1.0.0"},{"group":"","name":"go.uber.org/multierr","version":"v1.11.0","hashes":[{"alg":"SHA-256","content":"db4f90b622eacb435de8575007d4cb5da835d83b1092b6ecde1b4c15f0cdf346"}],"purl":"pkg:golang/go.uber.org/multierr@v1.11.0","type":"library","bom-ref":"pkg:golang/go.uber.org/multierr@v1.11.0"},{"group":"","name":"golang.org/x/mod","version":"v0.15.0","hashes":[{"alg":"SHA-256","content":"8536e606c3badbe7b29496e752d136306254c84ed05a4e3152a3c5ad1809fbb7"}],"purl":"pkg:golang/golang.org/x/mod@v0.15.0","type":"library","bom-ref":"pkg:golang/golang.org/x/mod@v0.15.0"},{"group":"","name":"golang.org/x/tools","version":"v0.18.0","hashes":[{"alg":"SHA-256","content":"18bec1e02c1c2cb7a8e7dcb1ffd5165ae34e5b59f7559e1fe5ac567cc2fb2dc8"}],"purl":"pkg:golang/golang.org/x/tools@v0.18.0","type":"library","bom-ref":"pkg:golang/golang.org/x/tools@v0.18.0"},{"group":"","name":"gopkg.in/natefinch/npipe.v2","version":"v2.0.0-20160621034901-c1b8fa8bdcce","hashes":[{"alg":"SHA-256","content":"e4071754736383e043c6bcb7f36fbc38aa27f1211688a92d411d3b44a3ecbf57"}],"purl":"pkg:golang/gopkg.in/natefinch/npipe.v2@v2.0.0-20160621034901-c1b8fa8bdcce","type":"library","bom-ref":"pkg:golang/gopkg.in/natefinch/npipe.v2@v2.0.0-20160621034901-c1b8fa8bdcce"},{"group":"","name":"lukechampine.com/blake3","version":"v1.2.1","hashes":[{"alg":"SHA-256","content":"d0e151a7b7c1b40ca519508ee34a3ceec6eea64c881a06e9bf5f8cd64d4b33a9"}],"purl":"pkg:golang/lukechampine.com/blake3@v1.2.1","type":"library","bom-ref":"pkg:golang/lukechampine.com/blake3@v1.2.1"},{"group":"","name":"lukechampine.com/uint128","version":"v1.2.0","hashes":[{"alg":"SHA-256","content":"73879623094419ac42ffe1f5560ba15383c75cd5830833149567485a5da3d609"}],"purl":"pkg:golang/lukechampine.com/uint128@v1.2.0","type":"library","bom-ref":"pkg:golang/lukechampine.com/uint128@v1.2.0"},{"group":"","name":"modernc.org/cc/v3","version":"v3.40.0","hashes":[{"alg":"SHA-256","content":"fdb4e0e1d9d69125e8c143bab2c40a9ce574c8c5710d8348b08af3a93143187d"}],"purl":"pkg:golang/modernc.org/cc/v3@v3.40.0","type":"library","bom-ref":"pkg:golang/modernc.org/cc/v3@v3.40.0"},{"group":"","name":"modernc.org/ccgo/v3","version":"v3.16.13","hashes":[{"alg":"SHA-256","content":"d90ba4fb9620a489a13e3bf642ca1bd439d9ff8b289b59494e876e6c87285246"}],"purl":"pkg:golang/modernc.org/ccgo/v3@v3.16.13","type":"library","bom-ref":"pkg:golang/modernc.org/ccgo/v3@v3.16.13"},{"group":"","name":"modernc.org/libc","version":"v1.29.0","hashes":[{"alg":"SHA-256","content":"0da1bfe10dcb45176aa622f23f40b69b507c64c1a443e70280e22312d4256214"}],"purl":"pkg:golang/modernc.org/libc@v1.29.0","type":"library","bom-ref":"pkg:golang/modernc.org/libc@v1.29.0"},{"group":"","name":"modernc.org/mathutil","version":"v1.6.0","hashes":[{"alg":"SHA-256","content":"522e50f6ad534768059b401046a4146815852c0850a42c0d72e84139279d58fa"}],"purl":"pkg:golang/modernc.org/mathutil@v1.6.0","type":"library","bom-ref":"pkg:golang/modernc.org/mathutil@v1.6.0"},{"group":"","name":"modernc.org/memory","version":"v1.7.2","hashes":[{"alg":"SHA-256","content":"34ee0d542432d0dee59fe4fd9e05aa3907e2ee57b2e2fa70bc0451f878f0f791"}],"purl":"pkg:golang/modernc.org/memory@v1.7.2","type":"library","bom-ref":"pkg:golang/modernc.org/memory@v1.7.2"},{"group":"","name":"modernc.org/opt","version":"v0.1.3","hashes":[{"alg":"SHA-256","content":"59d4a20797af0dc8a09c4ef482e40ac58525d789a05ad6c29518b9c269244d7d"}],"purl":"pkg:golang/modernc.org/opt@v0.1.3","type":"library","bom-ref":"pkg:golang/modernc.org/opt@v0.1.3"},{"group":"","name":"modernc.org/sqlite","version":"v1.27.0","hashes":[{"alg":"SHA-256","content":"431a5acf3d331fc675c421728b91922f71736ed6777ef6e39b2c0da2095d116d"}],"purl":"pkg:golang/modernc.org/sqlite@v1.27.0","type":"library","bom-ref":"pkg:golang/modernc.org/sqlite@v1.27.0"},{"group":"","name":"modernc.org/strutil","version":"v1.1.3","hashes":[{"alg":"SHA-256","content":"3041cd03b3dd1271302efb2944cb564cd9e9da79f2bcc7e48a64f534a34019bc"}],"purl":"pkg:golang/modernc.org/strutil@v1.1.3","type":"library","bom-ref":"pkg:golang/modernc.org/strutil@v1.1.3"},{"group":"","name":"modernc.org/token","version":"v1.0.1","hashes":[{"alg":"SHA-256","content":"506cceacd575980152101eb794e14722935151532f61373acaed52318fd74c33"}],"purl":"pkg:golang/modernc.org/token@v1.0.1","type":"library","bom-ref":"pkg:golang/modernc.org/token@v1.0.1"},{"group":"","name":"nhooyr.io/websocket","version":"v1.8.7","hashes":[{"alg":"SHA-256","content":"07bd0364ff086a423ae51550e7532c58fffc8e774d99adba0d503f9c5482816d"}],"purl":"pkg:golang/nhooyr.io/websocket@v1.8.7","type":"library","bom-ref":"pkg:golang/nhooyr.io/websocket@v1.8.7"},{"group":"","name":"github.com/ChainSafe/go-schnorrkel","version":"v0.0.0-20200405005733-88cbf1b4c40d","hashes":[{"alg":"SHA-256","content":"511757e7ebe0db9b6cdda0a1f07e48159c9b2582968491d83139dff942eda02e"}],"purl":"pkg:golang/github.com/ChainSafe/go-schnorrkel@v0.0.0-20200405005733-88cbf1b4c40d","type":"library","bom-ref":"pkg:golang/github.com/ChainSafe/go-schnorrkel@v0.0.0-20200405005733-88cbf1b4c40d"},{"group":"","name":"github.com/regen-network/protobuf","version":"v1.3.3-alpha.regen.1","hashes":[{"alg":"SHA-256","content":"d838d3151d4784c4218960b9b19e0e850dfe36d75b67aa010ca430ab93aef852"}],"purl":"pkg:golang/github.com/regen-network/protobuf@v1.3.3-alpha.regen.1","type":"library","bom-ref":"pkg:golang/github.com/regen-network/protobuf@v1.3.3-alpha.regen.1"},{"group":"actions","name":"checkout","version":"v2","purl":"pkg:github/actions/checkout@v2","type":"application","bom-ref":"pkg:github/actions/checkout@v2"},{"group":"actions","name":"setup-go","version":"v4","purl":"pkg:github/actions/setup-go@v4","type":"application","bom-ref":"pkg:github/actions/setup-go@v4"},{"group":"actions","name":"checkout","version":"v4","purl":"pkg:github/actions/checkout@v4","type":"application","bom-ref":"pkg:github/actions/checkout@v4"},{"group":"actions","name":"cache","version":"v3","purl":"pkg:github/actions/cache@v3","type":"application","bom-ref":"pkg:github/actions/cache@v3"},{"group":"","name":"github/codeql-action/init","version":"v3","purl":"pkg:github/github%2Fcodeql-action%2Finit@v3","type":"library","bom-ref":"pkg:github/github/codeql-action/init@v3"},{"group":"","name":"github/codeql-action/autobuild","version":"v3","purl":"pkg:github/github%2Fcodeql-action%2Fautobuild@v3","type":"library","bom-ref":"pkg:github/github/codeql-action/autobuild@v3"},{"group":"","name":"github/codeql-action/analyze","version":"v3","purl":"pkg:github/github%2Fcodeql-action%2Fanalyze@v3","type":"library","bom-ref":"pkg:github/github/codeql-action/analyze@v3"},{"group":"gaurav-nelson","name":"github-action-markdown-link-check","version":"1.0.15","purl":"pkg:github/gaurav-nelson/github-action-markdown-link-check@1.0.15","type":"library","bom-ref":"pkg:github/gaurav-nelson/github-action-markdown-link-check@1.0.15"},{"group":"amannn","name":"action-semantic-pull-request","version":"v5.4.0","purl":"pkg:github/amannn/action-semantic-pull-request@v5.4.0","type":"library","bom-ref":"pkg:github/amannn/action-semantic-pull-request@v5.4.0"},{"group":"actions","name":"checkout","version":"v3","purl":"pkg:github/actions/checkout@v3","type":"application","bom-ref":"pkg:github/actions/checkout@v3"},{"group":"actions","name":"upload-artifact","version":"v1","purl":"pkg:github/actions/upload-artifact@v1","type":"application","bom-ref":"pkg:github/actions/upload-artifact@v1"}],"services":[],"dependencies":[]}