{"$schema":"http://cyclonedx.org/schema/bom-1.5.schema.json","bomFormat":"CycloneDX","specVersion":"1.5","serialNumber":"urn:uuid:b94a6975-51b9-4a6f-96b4-0522d26ec7df","version":1,"metadata":{"timestamp":"2024-08-23T14:30:20Z","tools":{"components":[{"type":"application","author":"anchore","name":"syft","version":"1.11.0"}]},"component":{"bom-ref":"69bc9cdde2440749","type":"file","name":"https://github.com/ngrok/ngrok-go"}},"components":[{"bom-ref":"d1a26dfad774a478","type":"library","name":"../","purl":"pkg:golang/../","properties":[{"name":"syft:package:foundBy","value":"go-module-file-cataloger"},{"name":"syft:package:language","value":"go"},{"name":"syft:package:type","value":"go-module"},{"name":"syft:package:metadataType","value":"go-module-entry"},{"name":"syft:location:0:path","value":"/examples/go.mod"}]},{"bom-ref":"pkg:golang/../log/log15?package-id=7aa52c5243c499ad","type":"library","name":"../log/log15","cpe":"cpe:2.3:a:log:log15:*:*:*:*:*:*:*:*","purl":"pkg:golang/../log/log15","properties":[{"name":"syft:package:foundBy","value":"go-module-file-cataloger"},{"name":"syft:package:language","value":"go"},{"name":"syft:package:type","value":"go-module"},{"name":"syft:package:metadataType","value":"go-module-entry"},{"name":"syft:location:0:path","value":"/examples/go.mod"}]},{"bom-ref":"pkg:golang/../log/slog?package-id=90c3d47afb11dcc1","type":"library","name":"../log/slog","cpe":"cpe:2.3:a:log:slog:*:*:*:*:*:*:*:*","purl":"pkg:golang/../log/slog","properties":[{"name":"syft:package:foundBy","value":"go-module-file-cataloger"},{"name":"syft:package:language","value":"go"},{"name":"syft:package:type","value":"go-module"},{"name":"syft:package:metadataType","value":"go-module-entry"},{"name":"syft:location:0:path","value":"/examples/go.mod"}]},{"bom-ref":"pkg:github/hatsunemiku3939/direnv-action@v1?package-id=82b806785102a437","type":"library","name":"HatsuneMiku3939/direnv-action","version":"v1","cpe":"cpe:2.3:a:HatsuneMiku3939\\/direnv-action:HatsuneMiku3939\\/direnv-action:v1:*:*:*:*:*:*:*","purl":"pkg:github/HatsuneMiku3939/direnv-action@v1","properties":[{"name":"syft:package:foundBy","value":"github-actions-usage-cataloger"},{"name":"syft:package:type","value":"github-action"},{"name":"syft:cpe23","value":"cpe:2.3:a:HatsuneMiku3939\\/direnv-action:HatsuneMiku3939\\/direnv_action:v1:*:*:*:*:*:*:*"},{"name":"syft:cpe23","value":"cpe:2.3:a:HatsuneMiku3939\\/direnv_action:HatsuneMiku3939\\/direnv-action:v1:*:*:*:*:*:*:*"},{"name":"syft:cpe23","value":"cpe:2.3:a:HatsuneMiku3939\\/direnv_action:HatsuneMiku3939\\/direnv_action:v1:*:*:*:*:*:*:*"},{"name":"syft:cpe23","value":"cpe:2.3:a:HatsuneMiku3939\\/direnv:HatsuneMiku3939\\/direnv-action:v1:*:*:*:*:*:*:*"},{"name":"syft:cpe23","value":"cpe:2.3:a:HatsuneMiku3939\\/direnv:HatsuneMiku3939\\/direnv_action:v1:*:*:*:*:*:*:*"},{"name":"syft:location:0:path","value":"/.github/workflows/buildandtest.yml"}]},{"bom-ref":"pkg:github/hatsunemiku3939/direnv-action@v1?package-id=44df40dc6d9fe15b","type":"library","name":"HatsuneMiku3939/direnv-action","version":"v1","cpe":"cpe:2.3:a:HatsuneMiku3939\\/direnv-action:HatsuneMiku3939\\/direnv-action:v1:*:*:*:*:*:*:*","purl":"pkg:github/HatsuneMiku3939/direnv-action@v1","properties":[{"name":"syft:package:foundBy","value":"github-actions-usage-cataloger"},{"name":"syft:package:type","value":"github-action"},{"name":"syft:cpe23","value":"cpe:2.3:a:HatsuneMiku3939\\/direnv-action:HatsuneMiku3939\\/direnv_action:v1:*:*:*:*:*:*:*"},{"name":"syft:cpe23","value":"cpe:2.3:a:HatsuneMiku3939\\/direnv_action:HatsuneMiku3939\\/direnv-action:v1:*:*:*:*:*:*:*"},{"name":"syft:cpe23","value":"cpe:2.3:a:HatsuneMiku3939\\/direnv_action:HatsuneMiku3939\\/direnv_action:v1:*:*:*:*:*:*:*"},{"name":"syft:cpe23","value":"cpe:2.3:a:HatsuneMiku3939\\/direnv:HatsuneMiku3939\\/direnv-action:v1:*:*:*:*:*:*:*"},{"name":"syft:cpe23","value":"cpe:2.3:a:HatsuneMiku3939\\/direnv:HatsuneMiku3939\\/direnv_action:v1:*:*:*:*:*:*:*"},{"name":"syft:location:0:path","value":"/.github/workflows/lint.yml"}]},{"bom-ref":"pkg:github/actions/checkout@v3?package-id=a85afae767e6206e","type":"library","name":"actions/checkout","version":"v3","cpe":"cpe:2.3:a:actions\\/checkout:actions\\/checkout:v3:*:*:*:*:*:*:*","purl":"pkg:github/actions/checkout@v3","properties":[{"name":"syft:package:foundBy","value":"github-actions-usage-cataloger"},{"name":"syft:package:type","value":"github-action"},{"name":"syft:location:0:path","value":"/.github/workflows/buildandtest.yml"}]},{"bom-ref":"pkg:github/actions/checkout@v3?package-id=e9c259c76867c0c1","type":"library","name":"actions/checkout","version":"v3","cpe":"cpe:2.3:a:actions\\/checkout:actions\\/checkout:v3:*:*:*:*:*:*:*","purl":"pkg:github/actions/checkout@v3","properties":[{"name":"syft:package:foundBy","value":"github-actions-usage-cataloger"},{"name":"syft:package:type","value":"github-action"},{"name":"syft:location:0:path","value":"/.github/workflows/lint.yml"}]},{"bom-ref":"pkg:github/cachix/install-nix-action@v18?package-id=5b4f95d00776c006","type":"library","name":"cachix/install-nix-action","version":"v18","cpe":"cpe:2.3:a:cachix\\/install-nix-action:cachix\\/install-nix-action:v18:*:*:*:*:*:*:*","purl":"pkg:github/cachix/install-nix-action@v18","properties":[{"name":"syft:package:foundBy","value":"github-actions-usage-cataloger"},{"name":"syft:package:type","value":"github-action"},{"name":"syft:cpe23","value":"cpe:2.3:a:cachix\\/install-nix-action:cachix\\/install_nix_action:v18:*:*:*:*:*:*:*"},{"name":"syft:cpe23","value":"cpe:2.3:a:cachix\\/install_nix_action:cachix\\/install-nix-action:v18:*:*:*:*:*:*:*"},{"name":"syft:cpe23","value":"cpe:2.3:a:cachix\\/install_nix_action:cachix\\/install_nix_action:v18:*:*:*:*:*:*:*"},{"name":"syft:cpe23","value":"cpe:2.3:a:cachix\\/install-nix:cachix\\/install-nix-action:v18:*:*:*:*:*:*:*"},{"name":"syft:cpe23","value":"cpe:2.3:a:cachix\\/install-nix:cachix\\/install_nix_action:v18:*:*:*:*:*:*:*"},{"name":"syft:cpe23","value":"cpe:2.3:a:cachix\\/install_nix:cachix\\/install-nix-action:v18:*:*:*:*:*:*:*"},{"name":"syft:cpe23","value":"cpe:2.3:a:cachix\\/install_nix:cachix\\/install_nix_action:v18:*:*:*:*:*:*:*"},{"name":"syft:cpe23","value":"cpe:2.3:a:cachix\\/install:cachix\\/install-nix-action:v18:*:*:*:*:*:*:*"},{"name":"syft:cpe23","value":"cpe:2.3:a:cachix\\/install:cachix\\/install_nix_action:v18:*:*:*:*:*:*:*"},{"name":"syft:location:0:path","value":"/.github/workflows/buildandtest.yml"}]},{"bom-ref":"pkg:github/cachix/install-nix-action@v18?package-id=25c83f90bf8984db","type":"library","name":"cachix/install-nix-action","version":"v18","cpe":"cpe:2.3:a:cachix\\/install-nix-action:cachix\\/install-nix-action:v18:*:*:*:*:*:*:*","purl":"pkg:github/cachix/install-nix-action@v18","properties":[{"name":"syft:package:foundBy","value":"github-actions-usage-cataloger"},{"name":"syft:package:type","value":"github-action"},{"name":"syft:cpe23","value":"cpe:2.3:a:cachix\\/install-nix-action:cachix\\/install_nix_action:v18:*:*:*:*:*:*:*"},{"name":"syft:cpe23","value":"cpe:2.3:a:cachix\\/install_nix_action:cachix\\/install-nix-action:v18:*:*:*:*:*:*:*"},{"name":"syft:cpe23","value":"cpe:2.3:a:cachix\\/install_nix_action:cachix\\/install_nix_action:v18:*:*:*:*:*:*:*"},{"name":"syft:cpe23","value":"cpe:2.3:a:cachix\\/install-nix:cachix\\/install-nix-action:v18:*:*:*:*:*:*:*"},{"name":"syft:cpe23","value":"cpe:2.3:a:cachix\\/install-nix:cachix\\/install_nix_action:v18:*:*:*:*:*:*:*"},{"name":"syft:cpe23","value":"cpe:2.3:a:cachix\\/install_nix:cachix\\/install-nix-action:v18:*:*:*:*:*:*:*"},{"name":"syft:cpe23","value":"cpe:2.3:a:cachix\\/install_nix:cachix\\/install_nix_action:v18:*:*:*:*:*:*:*"},{"name":"syft:cpe23","value":"cpe:2.3:a:cachix\\/install:cachix\\/install-nix-action:v18:*:*:*:*:*:*:*"},{"name":"syft:cpe23","value":"cpe:2.3:a:cachix\\/install:cachix\\/install_nix_action:v18:*:*:*:*:*:*:*"},{"name":"syft:location:0:path","value":"/.github/workflows/lint.yml"}]},{"bom-ref":"pkg:golang/github.com/andybalholm/brotli@v1.1.0?package-id=d4737e92b3dce0f9","type":"library","name":"github.com/andybalholm/brotli","version":"v1.1.0","cpe":"cpe:2.3:a:andybalholm:brotli:v1.1.0:*:*:*:*:*:*:*","purl":"pkg:golang/github.com/andybalholm/brotli@v1.1.0","properties":[{"name":"syft:package:foundBy","value":"go-module-file-cataloger"},{"name":"syft:package:language","value":"go"},{"name":"syft:package:type","value":"go-module"},{"name":"syft:package:metadataType","value":"go-module-entry"},{"name":"syft:location:0:path","value":"/examples/go.mod"},{"name":"syft:metadata:h1Digest","value":"h1:eLKJA0d02Lf0mVpIDgYnqXcUn0GqVmEFny3VuID1U3M="}]},{"bom-ref":"pkg:golang/github.com/davecgh/go-spew@v1.1.1?package-id=4fff1eaa0bc0be66","type":"library","name":"github.com/davecgh/go-spew","version":"v1.1.1","cpe":"cpe:2.3:a:davecgh:go-spew:v1.1.1:*:*:*:*:*:*:*","purl":"pkg:golang/github.com/davecgh/go-spew@v1.1.1","properties":[{"name":"syft:package:foundBy","value":"go-module-file-cataloger"},{"name":"syft:package:language","value":"go"},{"name":"syft:package:type","value":"go-module"},{"name":"syft:package:metadataType","value":"go-module-entry"},{"name":"syft:cpe23","value":"cpe:2.3:a:davecgh:go_spew:v1.1.1:*:*:*:*:*:*:*"},{"name":"syft:location:0:path","value":"/go.mod"},{"name":"syft:metadata:h1Digest","value":"h1:vj9j/u1bqnvCEfJOwUhtlOARqs3+rkHYY13jYWTU97c="}]},{"bom-ref":"pkg:golang/github.com/go-stack/stack@v1.8.1?package-id=fdd06c20bf0b1fcc","type":"library","name":"github.com/go-stack/stack","version":"v1.8.1","cpe":"cpe:2.3:a:go-stack:stack:v1.8.1:*:*:*:*:*:*:*","purl":"pkg:golang/github.com/go-stack/stack@v1.8.1","properties":[{"name":"syft:package:foundBy","value":"go-module-file-cataloger"},{"name":"syft:package:language","value":"go"},{"name":"syft:package:type","value":"go-module"},{"name":"syft:package:metadataType","value":"go-module-entry"},{"name":"syft:cpe23","value":"cpe:2.3:a:go_stack:stack:v1.8.1:*:*:*:*:*:*:*"},{"name":"syft:cpe23","value":"cpe:2.3:a:go:stack:v1.8.1:*:*:*:*:*:*:*"},{"name":"syft:location:0:path","value":"/examples/go.mod"},{"name":"syft:metadata:h1Digest","value":"h1:ntEHSVwIt7PNXNpgPmVfMrNhLtgjlmnZha2kOpuRiDw="}]},{"bom-ref":"pkg:golang/github.com/go-stack/stack@v1.8.1?package-id=ba64cf70a25d0346","type":"library","name":"github.com/go-stack/stack","version":"v1.8.1","cpe":"cpe:2.3:a:go-stack:stack:v1.8.1:*:*:*:*:*:*:*","purl":"pkg:golang/github.com/go-stack/stack@v1.8.1","properties":[{"name":"syft:package:foundBy","value":"go-module-file-cataloger"},{"name":"syft:package:language","value":"go"},{"name":"syft:package:type","value":"go-module"},{"name":"syft:package:metadataType","value":"go-module-entry"},{"name":"syft:cpe23","value":"cpe:2.3:a:go_stack:stack:v1.8.1:*:*:*:*:*:*:*"},{"name":"syft:cpe23","value":"cpe:2.3:a:go:stack:v1.8.1:*:*:*:*:*:*:*"},{"name":"syft:location:0:path","value":"/go.mod"},{"name":"syft:metadata:h1Digest","value":"h1:ntEHSVwIt7PNXNpgPmVfMrNhLtgjlmnZha2kOpuRiDw="}]},{"bom-ref":"pkg:golang/github.com/google/go-cmp@v0.5.8?package-id=0b9457f24f3520d6","type":"library","name":"github.com/google/go-cmp","version":"v0.5.8","cpe":"cpe:2.3:a:google:go-cmp:v0.5.8:*:*:*:*:*:*:*","purl":"pkg:golang/github.com/google/go-cmp@v0.5.8","properties":[{"name":"syft:package:foundBy","value":"go-module-file-cataloger"},{"name":"syft:package:language","value":"go"},{"name":"syft:package:type","value":"go-module"},{"name":"syft:package:metadataType","value":"go-module-entry"},{"name":"syft:cpe23","value":"cpe:2.3:a:google:go_cmp:v0.5.8:*:*:*:*:*:*:*"},{"name":"syft:location:0:path","value":"/examples/go.mod"},{"name":"syft:metadata:h1Digest","value":"h1:e6P7q2lk1O+qJJb4BtCQXlK8vWEO8V1ZeuEdJNOqZyg="}]},{"bom-ref":"pkg:golang/github.com/inconshreveable/log15@v3.0.0-testing.3%2Bincompatible?package-id=3e46703bdb5039c2","type":"library","name":"github.com/inconshreveable/log15","version":"v3.0.0-testing.3+incompatible","cpe":"cpe:2.3:a:inconshreveable:log15:v3.0.0-testing.3\\+incompatible:*:*:*:*:*:*:*","purl":"pkg:golang/github.com/inconshreveable/log15@v3.0.0-testing.3%2Bincompatible","properties":[{"name":"syft:package:foundBy","value":"go-module-file-cataloger"},{"name":"syft:package:language","value":"go"},{"name":"syft:package:type","value":"go-module"},{"name":"syft:package:metadataType","value":"go-module-entry"},{"name":"syft:location:0:path","value":"/examples/go.mod"},{"name":"syft:metadata:h1Digest","value":"h1:zaX5fYT98jX5j4UhO/WbfY8T1HkgVrydiDMC9PWqGCo="}]},{"bom-ref":"pkg:golang/github.com/inconshreveable/log15@v3.0.0-testing.3%2Bincompatible?package-id=08c56d52302f3f5a","type":"library","name":"github.com/inconshreveable/log15","version":"v3.0.0-testing.3+incompatible","cpe":"cpe:2.3:a:inconshreveable:log15:v3.0.0-testing.3\\+incompatible:*:*:*:*:*:*:*","purl":"pkg:golang/github.com/inconshreveable/log15@v3.0.0-testing.3%2Bincompatible","properties":[{"name":"syft:package:foundBy","value":"go-module-file-cataloger"},{"name":"syft:package:language","value":"go"},{"name":"syft:package:type","value":"go-module"},{"name":"syft:package:metadataType","value":"go-module-entry"},{"name":"syft:location:0:path","value":"/go.mod"},{"name":"syft:metadata:h1Digest","value":"h1:zaX5fYT98jX5j4UhO/WbfY8T1HkgVrydiDMC9PWqGCo="}]},{"bom-ref":"pkg:golang/github.com/inconshreveable/log15@v3.0.0-testing.1?package-id=ca041e99d7a36874#v3","type":"library","name":"github.com/inconshreveable/log15/v3","version":"v3.0.0-testing.1","cpe":"cpe:2.3:a:inconshreveable:log15\\/v3:v3.0.0-testing.1:*:*:*:*:*:*:*","purl":"pkg:golang/github.com/inconshreveable/log15@v3.0.0-testing.1#v3","properties":[{"name":"syft:package:foundBy","value":"go-module-file-cataloger"},{"name":"syft:package:language","value":"go"},{"name":"syft:package:type","value":"go-module"},{"name":"syft:package:metadataType","value":"go-module-entry"},{"name":"syft:location:0:path","value":"/log/log15/go.mod"},{"name":"syft:metadata:h1Digest","value":"h1:z0j/cq0uyipqKQU6RxLmK0yLhebUG91QcQ/yXxlurRI="}]},{"bom-ref":"pkg:golang/github.com/inconshreveable/log15@v3.0.0-testing.5?package-id=4ce94c4bfc073e60#v3","type":"library","name":"github.com/inconshreveable/log15/v3","version":"v3.0.0-testing.5","cpe":"cpe:2.3:a:inconshreveable:log15\\/v3:v3.0.0-testing.5:*:*:*:*:*:*:*","purl":"pkg:golang/github.com/inconshreveable/log15@v3.0.0-testing.5#v3","properties":[{"name":"syft:package:foundBy","value":"go-module-file-cataloger"},{"name":"syft:package:language","value":"go"},{"name":"syft:package:type","value":"go-module"},{"name":"syft:package:metadataType","value":"go-module-entry"},{"name":"syft:location:0:path","value":"/examples/go.mod"},{"name":"syft:metadata:h1Digest","value":"h1:h4e0f3kjgg+RJBlKOabrohjHe47D3bbAB9BgMrc3DYA="}]},{"bom-ref":"pkg:golang/github.com/inconshreveable/log15@v3.0.0-testing.5?package-id=a681743e075f2e60#v3","type":"library","name":"github.com/inconshreveable/log15/v3","version":"v3.0.0-testing.5","cpe":"cpe:2.3:a:inconshreveable:log15\\/v3:v3.0.0-testing.5:*:*:*:*:*:*:*","purl":"pkg:golang/github.com/inconshreveable/log15@v3.0.0-testing.5#v3","properties":[{"name":"syft:package:foundBy","value":"go-module-file-cataloger"},{"name":"syft:package:language","value":"go"},{"name":"syft:package:type","value":"go-module"},{"name":"syft:package:metadataType","value":"go-module-entry"},{"name":"syft:location:0:path","value":"/go.mod"},{"name":"syft:metadata:h1Digest","value":"h1:h4e0f3kjgg+RJBlKOabrohjHe47D3bbAB9BgMrc3DYA="}]},{"bom-ref":"pkg:golang/github.com/jpillora/backoff@v1.0.0?package-id=45595f5b7078ba98","type":"library","name":"github.com/jpillora/backoff","version":"v1.0.0","cpe":"cpe:2.3:a:jpillora:backoff:v1.0.0:*:*:*:*:*:*:*","purl":"pkg:golang/github.com/jpillora/backoff@v1.0.0","properties":[{"name":"syft:package:foundBy","value":"go-module-file-cataloger"},{"name":"syft:package:language","value":"go"},{"name":"syft:package:type","value":"go-module"},{"name":"syft:package:metadataType","value":"go-module-entry"},{"name":"syft:location:0:path","value":"/examples/go.mod"},{"name":"syft:metadata:h1Digest","value":"h1:uvFg412JmmHBHw7iwprIxkPMI+sGQ4kzOWsMeHnm2EA="}]},{"bom-ref":"pkg:golang/github.com/jpillora/backoff@v1.0.0?package-id=d85183de8aa1e79d","type":"library","name":"github.com/jpillora/backoff","version":"v1.0.0","cpe":"cpe:2.3:a:jpillora:backoff:v1.0.0:*:*:*:*:*:*:*","purl":"pkg:golang/github.com/jpillora/backoff@v1.0.0","properties":[{"name":"syft:package:foundBy","value":"go-module-file-cataloger"},{"name":"syft:package:language","value":"go"},{"name":"syft:package:type","value":"go-module"},{"name":"syft:package:metadataType","value":"go-module-entry"},{"name":"syft:location:0:path","value":"/go.mod"},{"name":"syft:metadata:h1Digest","value":"h1:uvFg412JmmHBHw7iwprIxkPMI+sGQ4kzOWsMeHnm2EA="}]},{"bom-ref":"pkg:golang/github.com/klauspost/compress@v1.17.6?package-id=f493e88d730c844d","type":"library","name":"github.com/klauspost/compress","version":"v1.17.6","cpe":"cpe:2.3:a:klauspost:compress:v1.17.6:*:*:*:*:*:*:*","purl":"pkg:golang/github.com/klauspost/compress@v1.17.6","properties":[{"name":"syft:package:foundBy","value":"go-module-file-cataloger"},{"name":"syft:package:language","value":"go"},{"name":"syft:package:type","value":"go-module"},{"name":"syft:package:metadataType","value":"go-module-entry"},{"name":"syft:location:0:path","value":"/examples/go.mod"},{"name":"syft:metadata:h1Digest","value":"h1:60eq2E/jlfwQXtvZEeBUYADs+BwKBWURIY+Gj2eRGjI="}]},{"bom-ref":"pkg:golang/github.com/mattn/go-colorable@v0.1.13?package-id=0f89e118f7216688","type":"library","name":"github.com/mattn/go-colorable","version":"v0.1.13","cpe":"cpe:2.3:a:mattn:go-colorable:v0.1.13:*:*:*:*:*:*:*","purl":"pkg:golang/github.com/mattn/go-colorable@v0.1.13","properties":[{"name":"syft:package:foundBy","value":"go-module-file-cataloger"},{"name":"syft:package:language","value":"go"},{"name":"syft:package:type","value":"go-module"},{"name":"syft:package:metadataType","value":"go-module-entry"},{"name":"syft:cpe23","value":"cpe:2.3:a:mattn:go_colorable:v0.1.13:*:*:*:*:*:*:*"},{"name":"syft:location:0:path","value":"/examples/go.mod"},{"name":"syft:metadata:h1Digest","value":"h1:fFA4WZxdEF4tXPZVKMLwD8oUnCTTo08duU7wxecdEvA="}]},{"bom-ref":"pkg:golang/github.com/mattn/go-colorable@v0.1.13?package-id=898b7c8b52706e63","type":"library","name":"github.com/mattn/go-colorable","version":"v0.1.13","cpe":"cpe:2.3:a:mattn:go-colorable:v0.1.13:*:*:*:*:*:*:*","purl":"pkg:golang/github.com/mattn/go-colorable@v0.1.13","properties":[{"name":"syft:package:foundBy","value":"go-module-file-cataloger"},{"name":"syft:package:language","value":"go"},{"name":"syft:package:type","value":"go-module"},{"name":"syft:package:metadataType","value":"go-module-entry"},{"name":"syft:cpe23","value":"cpe:2.3:a:mattn:go_colorable:v0.1.13:*:*:*:*:*:*:*"},{"name":"syft:location:0:path","value":"/go.mod"},{"name":"syft:metadata:h1Digest","value":"h1:fFA4WZxdEF4tXPZVKMLwD8oUnCTTo08duU7wxecdEvA="}]},{"bom-ref":"pkg:golang/github.com/mattn/go-colorable@v0.1.13?package-id=d9481eead215f73f","type":"library","name":"github.com/mattn/go-colorable","version":"v0.1.13","cpe":"cpe:2.3:a:mattn:go-colorable:v0.1.13:*:*:*:*:*:*:*","purl":"pkg:golang/github.com/mattn/go-colorable@v0.1.13","properties":[{"name":"syft:package:foundBy","value":"go-module-file-cataloger"},{"name":"syft:package:language","value":"go"},{"name":"syft:package:type","value":"go-module"},{"name":"syft:package:metadataType","value":"go-module-entry"},{"name":"syft:cpe23","value":"cpe:2.3:a:mattn:go_colorable:v0.1.13:*:*:*:*:*:*:*"},{"name":"syft:location:0:path","value":"/log/log15/go.mod"},{"name":"syft:metadata:h1Digest","value":"h1:fFA4WZxdEF4tXPZVKMLwD8oUnCTTo08duU7wxecdEvA="}]},{"bom-ref":"pkg:golang/github.com/mattn/go-isatty@v0.0.16?package-id=cc28034cb89dbf27","type":"library","name":"github.com/mattn/go-isatty","version":"v0.0.16","cpe":"cpe:2.3:a:mattn:go-isatty:v0.0.16:*:*:*:*:*:*:*","purl":"pkg:golang/github.com/mattn/go-isatty@v0.0.16","properties":[{"name":"syft:package:foundBy","value":"go-module-file-cataloger"},{"name":"syft:package:language","value":"go"},{"name":"syft:package:type","value":"go-module"},{"name":"syft:package:metadataType","value":"go-module-entry"},{"name":"syft:cpe23","value":"cpe:2.3:a:mattn:go_isatty:v0.0.16:*:*:*:*:*:*:*"},{"name":"syft:location:0:path","value":"/examples/go.mod"},{"name":"syft:metadata:h1Digest","value":"h1:bq3VjFmv/sOjHtdEhmkEV4x1AJtvUvOJ2PFAZ5+peKQ="}]},{"bom-ref":"pkg:golang/github.com/mattn/go-isatty@v0.0.16?package-id=6480e02114a5d35d","type":"library","name":"github.com/mattn/go-isatty","version":"v0.0.16","cpe":"cpe:2.3:a:mattn:go-isatty:v0.0.16:*:*:*:*:*:*:*","purl":"pkg:golang/github.com/mattn/go-isatty@v0.0.16","properties":[{"name":"syft:package:foundBy","value":"go-module-file-cataloger"},{"name":"syft:package:language","value":"go"},{"name":"syft:package:type","value":"go-module"},{"name":"syft:package:metadataType","value":"go-module-entry"},{"name":"syft:cpe23","value":"cpe:2.3:a:mattn:go_isatty:v0.0.16:*:*:*:*:*:*:*"},{"name":"syft:location:0:path","value":"/go.mod"},{"name":"syft:metadata:h1Digest","value":"h1:bq3VjFmv/sOjHtdEhmkEV4x1AJtvUvOJ2PFAZ5+peKQ="}]},{"bom-ref":"pkg:golang/github.com/mattn/go-isatty@v0.0.16?package-id=fe7af9bf30a11e23","type":"library","name":"github.com/mattn/go-isatty","version":"v0.0.16","cpe":"cpe:2.3:a:mattn:go-isatty:v0.0.16:*:*:*:*:*:*:*","purl":"pkg:golang/github.com/mattn/go-isatty@v0.0.16","properties":[{"name":"syft:package:foundBy","value":"go-module-file-cataloger"},{"name":"syft:package:language","value":"go"},{"name":"syft:package:type","value":"go-module"},{"name":"syft:package:metadataType","value":"go-module-entry"},{"name":"syft:cpe23","value":"cpe:2.3:a:mattn:go_isatty:v0.0.16:*:*:*:*:*:*:*"},{"name":"syft:location:0:path","value":"/log/log15/go.mod"},{"name":"syft:metadata:h1Digest","value":"h1:bq3VjFmv/sOjHtdEhmkEV4x1AJtvUvOJ2PFAZ5+peKQ="}]},{"bom-ref":"pkg:golang/github.com/pmezard/go-difflib@v1.0.0?package-id=2e9153c8c5a4f906","type":"library","name":"github.com/pmezard/go-difflib","version":"v1.0.0","cpe":"cpe:2.3:a:pmezard:go-difflib:v1.0.0:*:*:*:*:*:*:*","purl":"pkg:golang/github.com/pmezard/go-difflib@v1.0.0","properties":[{"name":"syft:package:foundBy","value":"go-module-file-cataloger"},{"name":"syft:package:language","value":"go"},{"name":"syft:package:type","value":"go-module"},{"name":"syft:package:metadataType","value":"go-module-entry"},{"name":"syft:cpe23","value":"cpe:2.3:a:pmezard:go_difflib:v1.0.0:*:*:*:*:*:*:*"},{"name":"syft:location:0:path","value":"/go.mod"},{"name":"syft:metadata:h1Digest","value":"h1:4DBwDE0NGyQoBHbLQYPwSUPoCMWR5BEzIk/f1lZbAQM="}]},{"bom-ref":"pkg:golang/github.com/sirupsen/logrus@v1.9.0?package-id=05e87477f45f2a01","type":"library","name":"github.com/sirupsen/logrus","version":"v1.9.0","cpe":"cpe:2.3:a:sirupsen:logrus:v1.9.0:*:*:*:*:*:*:*","purl":"pkg:golang/github.com/sirupsen/logrus@v1.9.0","properties":[{"name":"syft:package:foundBy","value":"go-module-file-cataloger"},{"name":"syft:package:language","value":"go"},{"name":"syft:package:type","value":"go-module"},{"name":"syft:package:metadataType","value":"go-module-entry"},{"name":"syft:location:0:path","value":"/log/logrus/go.mod"},{"name":"syft:metadata:h1Digest","value":"h1:trlNQbNUG3OdDrDil03MCb1H2o9nJ1x4/5LYw7byDE0="}]},{"bom-ref":"pkg:golang/github.com/stretchr/testify@v1.8.0?package-id=49daa11c524cf52c","type":"library","name":"github.com/stretchr/testify","version":"v1.8.0","cpe":"cpe:2.3:a:stretchr:testify:v1.8.0:*:*:*:*:*:*:*","purl":"pkg:golang/github.com/stretchr/testify@v1.8.0","properties":[{"name":"syft:package:foundBy","value":"go-module-file-cataloger"},{"name":"syft:package:language","value":"go"},{"name":"syft:package:type","value":"go-module"},{"name":"syft:package:metadataType","value":"go-module-entry"},{"name":"syft:location:0:path","value":"/log/logrus/go.mod"},{"name":"syft:metadata:h1Digest","value":"h1:pSgiaMZlXftHpm5L7V1+rVB+AZJydKsMxsQBIJw4PKk="}]},{"bom-ref":"pkg:golang/github.com/stretchr/testify@v1.8.4?package-id=67c3f697edf388d0","type":"library","name":"github.com/stretchr/testify","version":"v1.8.4","cpe":"cpe:2.3:a:stretchr:testify:v1.8.4:*:*:*:*:*:*:*","purl":"pkg:golang/github.com/stretchr/testify@v1.8.4","properties":[{"name":"syft:package:foundBy","value":"go-module-file-cataloger"},{"name":"syft:package:language","value":"go"},{"name":"syft:package:type","value":"go-module"},{"name":"syft:package:metadataType","value":"go-module-entry"},{"name":"syft:location:0:path","value":"/go.mod"},{"name":"syft:metadata:h1Digest","value":"h1:CcVxjf3Q8PM0mHUKJCdn+eZZtm5yQwehR5yeSVQQcUk="}]},{"bom-ref":"pkg:golang/github.com/valyala/bytebufferpool@v1.0.0?package-id=3a3b0f9afcfc1d30","type":"library","name":"github.com/valyala/bytebufferpool","version":"v1.0.0","cpe":"cpe:2.3:a:valyala:bytebufferpool:v1.0.0:*:*:*:*:*:*:*","purl":"pkg:golang/github.com/valyala/bytebufferpool@v1.0.0","properties":[{"name":"syft:package:foundBy","value":"go-module-file-cataloger"},{"name":"syft:package:language","value":"go"},{"name":"syft:package:type","value":"go-module"},{"name":"syft:package:metadataType","value":"go-module-entry"},{"name":"syft:location:0:path","value":"/examples/go.mod"},{"name":"syft:metadata:h1Digest","value":"h1:GqA5TC/0021Y/b9FG4Oi9Mr3q7XYx6KllzawFIhcdPw="}]},{"bom-ref":"pkg:golang/github.com/valyala/fasthttp@v1.52.0?package-id=398c6991237872b5","type":"library","name":"github.com/valyala/fasthttp","version":"v1.52.0","cpe":"cpe:2.3:a:fasthttp_project:fasthttp:v1.52.0:*:*:*:*:*:*:*","purl":"pkg:golang/github.com/valyala/fasthttp@v1.52.0","properties":[{"name":"syft:package:foundBy","value":"go-module-file-cataloger"},{"name":"syft:package:language","value":"go"},{"name":"syft:package:type","value":"go-module"},{"name":"syft:package:metadataType","value":"go-module-entry"},{"name":"syft:location:0:path","value":"/examples/go.mod"},{"name":"syft:metadata:h1Digest","value":"h1:wqBQpxH71XW0e2g+Og4dzQM8pk34aFYlA1Ga8db7gU0="}]},{"bom-ref":"pkg:golang/go.uber.org/atomic@v1.7.0?package-id=793a806d77508b18","type":"library","name":"go.uber.org/atomic","version":"v1.7.0","purl":"pkg:golang/go.uber.org/atomic@v1.7.0","properties":[{"name":"syft:package:foundBy","value":"go-module-file-cataloger"},{"name":"syft:package:language","value":"go"},{"name":"syft:package:type","value":"go-module"},{"name":"syft:package:metadataType","value":"go-module-entry"},{"name":"syft:location:0:path","value":"/log/zap/go.mod"},{"name":"syft:metadata:h1Digest","value":"h1:ADUqmZGgLDDfbSL9ZmPxKTybcoEYHgpYfELNoN+7hsw="}]},{"bom-ref":"pkg:golang/go.uber.org/multierr@v1.11.0?package-id=45946a69b1708a6f","type":"library","name":"go.uber.org/multierr","version":"v1.11.0","purl":"pkg:golang/go.uber.org/multierr@v1.11.0","properties":[{"name":"syft:package:foundBy","value":"go-module-file-cataloger"},{"name":"syft:package:language","value":"go"},{"name":"syft:package:type","value":"go-module"},{"name":"syft:package:metadataType","value":"go-module-entry"},{"name":"syft:location:0:path","value":"/examples/go.mod"},{"name":"syft:metadata:h1Digest","value":"h1:blXXJkSxSSfBVBlC76pxqeO+LN3aDfLQo+309xJstO0="}]},{"bom-ref":"pkg:golang/go.uber.org/multierr@v1.11.0?package-id=ef196337207eb800","type":"library","name":"go.uber.org/multierr","version":"v1.11.0","purl":"pkg:golang/go.uber.org/multierr@v1.11.0","properties":[{"name":"syft:package:foundBy","value":"go-module-file-cataloger"},{"name":"syft:package:language","value":"go"},{"name":"syft:package:type","value":"go-module"},{"name":"syft:package:metadataType","value":"go-module-entry"},{"name":"syft:location:0:path","value":"/go.mod"},{"name":"syft:metadata:h1Digest","value":"h1:blXXJkSxSSfBVBlC76pxqeO+LN3aDfLQo+309xJstO0="}]},{"bom-ref":"pkg:golang/go.uber.org/multierr@v1.6.0?package-id=b53a48d368d5fb8e","type":"library","name":"go.uber.org/multierr","version":"v1.6.0","purl":"pkg:golang/go.uber.org/multierr@v1.6.0","properties":[{"name":"syft:package:foundBy","value":"go-module-file-cataloger"},{"name":"syft:package:language","value":"go"},{"name":"syft:package:type","value":"go-module"},{"name":"syft:package:metadataType","value":"go-module-entry"},{"name":"syft:location:0:path","value":"/log/zap/go.mod"},{"name":"syft:metadata:h1Digest","value":"h1:y6IPFStTAIT5Ytl7/XYmHvzXQ7S3g/IeZW9hyZ5thw4="}]},{"bom-ref":"pkg:golang/go.uber.org/zap@v1.23.0?package-id=89fd7d7acc12257a","type":"library","name":"go.uber.org/zap","version":"v1.23.0","purl":"pkg:golang/go.uber.org/zap@v1.23.0","properties":[{"name":"syft:package:foundBy","value":"go-module-file-cataloger"},{"name":"syft:package:language","value":"go"},{"name":"syft:package:type","value":"go-module"},{"name":"syft:package:metadataType","value":"go-module-entry"},{"name":"syft:location:0:path","value":"/log/zap/go.mod"},{"name":"syft:metadata:h1Digest","value":"h1:OjGQ5KQDEUawVHxNwQgPpiypGHOxo2mNZsOqTak4fFY="}]},{"bom-ref":"pkg:golang/golang.ngrok.com/muxado/v2@v2.0.0?package-id=db332d8cfd8c112a","type":"library","name":"golang.ngrok.com/muxado/v2","version":"v2.0.0","cpe":"cpe:2.3:a:muxado:v2:v2.0.0:*:*:*:*:*:*:*","purl":"pkg:golang/golang.ngrok.com/muxado/v2@v2.0.0","properties":[{"name":"syft:package:foundBy","value":"go-module-file-cataloger"},{"name":"syft:package:language","value":"go"},{"name":"syft:package:type","value":"go-module"},{"name":"syft:package:metadataType","value":"go-module-entry"},{"name":"syft:location:0:path","value":"/examples/go.mod"},{"name":"syft:metadata:h1Digest","value":"h1:bu9eIDhRdYNtIXNnqat/HyMeHYOAbUH55ebD7gTvW6c="}]},{"bom-ref":"pkg:golang/golang.ngrok.com/muxado/v2@v2.0.0?package-id=cf6cc5055e20ae1d","type":"library","name":"golang.ngrok.com/muxado/v2","version":"v2.0.0","cpe":"cpe:2.3:a:muxado:v2:v2.0.0:*:*:*:*:*:*:*","purl":"pkg:golang/golang.ngrok.com/muxado/v2@v2.0.0","properties":[{"name":"syft:package:foundBy","value":"go-module-file-cataloger"},{"name":"syft:package:language","value":"go"},{"name":"syft:package:type","value":"go-module"},{"name":"syft:package:metadataType","value":"go-module-entry"},{"name":"syft:location:0:path","value":"/go.mod"},{"name":"syft:metadata:h1Digest","value":"h1:bu9eIDhRdYNtIXNnqat/HyMeHYOAbUH55ebD7gTvW6c="}]},{"bom-ref":"pkg:golang/golang.org/x/net@v0.15.0?package-id=f20a635842f6a098","type":"library","name":"golang.org/x/net","version":"v0.15.0","cpe":"cpe:2.3:a:golang:networking:v0.15.0:*:*:*:*:go:*:*","purl":"pkg:golang/golang.org/x/net@v0.15.0","properties":[{"name":"syft:package:foundBy","value":"go-module-file-cataloger"},{"name":"syft:package:language","value":"go"},{"name":"syft:package:type","value":"go-module"},{"name":"syft:package:metadataType","value":"go-module-entry"},{"name":"syft:location:0:path","value":"/go.mod"},{"name":"syft:metadata:h1Digest","value":"h1:ugBLEUaxABaB5AJqW9enI0ACdci2RUd4eP51NTBvuJ8="}]},{"bom-ref":"pkg:golang/golang.org/x/net@v0.21.0?package-id=1e395cd586ad7cbb","type":"library","name":"golang.org/x/net","version":"v0.21.0","cpe":"cpe:2.3:a:golang:networking:v0.21.0:*:*:*:*:go:*:*","purl":"pkg:golang/golang.org/x/net@v0.21.0","properties":[{"name":"syft:package:foundBy","value":"go-module-file-cataloger"},{"name":"syft:package:language","value":"go"},{"name":"syft:package:type","value":"go-module"},{"name":"syft:package:metadataType","value":"go-module-entry"},{"name":"syft:location:0:path","value":"/examples/go.mod"}]},{"bom-ref":"pkg:golang/golang.org/x/sync@v0.3.0?package-id=9cd7d3f4c48adf40","type":"library","name":"golang.org/x/sync","version":"v0.3.0","cpe":"cpe:2.3:a:golang:x\\/sync:v0.3.0:*:*:*:*:*:*:*","purl":"pkg:golang/golang.org/x/sync@v0.3.0","properties":[{"name":"syft:package:foundBy","value":"go-module-file-cataloger"},{"name":"syft:package:language","value":"go"},{"name":"syft:package:type","value":"go-module"},{"name":"syft:package:metadataType","value":"go-module-entry"},{"name":"syft:location:0:path","value":"/examples/go.mod"},{"name":"syft:metadata:h1Digest","value":"h1:ftCYgMx6zT/asHUrPw8BLLscYtGznsLAnjq5RH9P66E="}]},{"bom-ref":"pkg:golang/golang.org/x/sync@v0.3.0?package-id=282b90465bf927eb","type":"library","name":"golang.org/x/sync","version":"v0.3.0","cpe":"cpe:2.3:a:golang:x\\/sync:v0.3.0:*:*:*:*:*:*:*","purl":"pkg:golang/golang.org/x/sync@v0.3.0","properties":[{"name":"syft:package:foundBy","value":"go-module-file-cataloger"},{"name":"syft:package:language","value":"go"},{"name":"syft:package:type","value":"go-module"},{"name":"syft:package:metadataType","value":"go-module-entry"},{"name":"syft:location:0:path","value":"/go.mod"},{"name":"syft:metadata:h1Digest","value":"h1:ftCYgMx6zT/asHUrPw8BLLscYtGznsLAnjq5RH9P66E="}]},{"bom-ref":"pkg:golang/golang.org/x/sys@v0.0.0-20220728004956-3c1f35247d10?package-id=d04a4ca36f5e312e","type":"library","name":"golang.org/x/sys","version":"v0.0.0-20220728004956-3c1f35247d10","cpe":"cpe:2.3:a:golang:x\\/sys:v0.0.0-20220728004956-3c1f35247d10:*:*:*:*:*:*:*","purl":"pkg:golang/golang.org/x/sys@v0.0.0-20220728004956-3c1f35247d10","properties":[{"name":"syft:package:foundBy","value":"go-module-file-cataloger"},{"name":"syft:package:language","value":"go"},{"name":"syft:package:type","value":"go-module"},{"name":"syft:package:metadataType","value":"go-module-entry"},{"name":"syft:location:0:path","value":"/log/logrus/go.mod"},{"name":"syft:metadata:h1Digest","value":"h1:WIoqL4EROvwiPdUtaip4VcDdpZ4kha7wBWZrbVKCIZg="}]},{"bom-ref":"pkg:golang/golang.org/x/sys@v0.12.0?package-id=552b6df7e0783069","type":"library","name":"golang.org/x/sys","version":"v0.12.0","cpe":"cpe:2.3:a:golang:x\\/sys:v0.12.0:*:*:*:*:*:*:*","purl":"pkg:golang/golang.org/x/sys@v0.12.0","properties":[{"name":"syft:package:foundBy","value":"go-module-file-cataloger"},{"name":"syft:package:language","value":"go"},{"name":"syft:package:type","value":"go-module"},{"name":"syft:package:metadataType","value":"go-module-entry"},{"name":"syft:location:0:path","value":"/go.mod"},{"name":"syft:metadata:h1Digest","value":"h1:CM0HF96J0hcLAwsHPJZjfdNzs0gftsLfgKt57wWHJ0o="}]},{"bom-ref":"pkg:golang/golang.org/x/sys@v0.17.0?package-id=d7d04c00d0706ad1","type":"library","name":"golang.org/x/sys","version":"v0.17.0","cpe":"cpe:2.3:a:golang:x\\/sys:v0.17.0:*:*:*:*:*:*:*","purl":"pkg:golang/golang.org/x/sys@v0.17.0","properties":[{"name":"syft:package:foundBy","value":"go-module-file-cataloger"},{"name":"syft:package:language","value":"go"},{"name":"syft:package:type","value":"go-module"},{"name":"syft:package:metadataType","value":"go-module-entry"},{"name":"syft:location:0:path","value":"/examples/go.mod"}]},{"bom-ref":"pkg:golang/golang.org/x/sys@v0.2.0?package-id=05e6a76d91f0ba9b","type":"library","name":"golang.org/x/sys","version":"v0.2.0","cpe":"cpe:2.3:a:golang:x\\/sys:v0.2.0:*:*:*:*:*:*:*","purl":"pkg:golang/golang.org/x/sys@v0.2.0","properties":[{"name":"syft:package:foundBy","value":"go-module-file-cataloger"},{"name":"syft:package:language","value":"go"},{"name":"syft:package:type","value":"go-module"},{"name":"syft:package:metadataType","value":"go-module-entry"},{"name":"syft:location:0:path","value":"/log/log15/go.mod"},{"name":"syft:metadata:h1Digest","value":"h1:ljd4t30dBnAvMZaQCevtY0xLLD0A+bRZXbgLMLU1F/A="}]},{"bom-ref":"pkg:golang/golang.org/x/term@v0.12.0?package-id=a802586bceba7d88","type":"library","name":"golang.org/x/term","version":"v0.12.0","cpe":"cpe:2.3:a:golang:x\\/term:v0.12.0:*:*:*:*:*:*:*","purl":"pkg:golang/golang.org/x/term@v0.12.0","properties":[{"name":"syft:package:foundBy","value":"go-module-file-cataloger"},{"name":"syft:package:language","value":"go"},{"name":"syft:package:type","value":"go-module"},{"name":"syft:package:metadataType","value":"go-module-entry"},{"name":"syft:location:0:path","value":"/go.mod"},{"name":"syft:metadata:h1Digest","value":"h1:/ZfYdc3zq+q02Rv9vGqTeSItdzZTSNDmfTi0mBAuidU="}]},{"bom-ref":"pkg:golang/golang.org/x/term@v0.17.0?package-id=9a070edb4e2a2189","type":"library","name":"golang.org/x/term","version":"v0.17.0","cpe":"cpe:2.3:a:golang:x\\/term:v0.17.0:*:*:*:*:*:*:*","purl":"pkg:golang/golang.org/x/term@v0.17.0","properties":[{"name":"syft:package:foundBy","value":"go-module-file-cataloger"},{"name":"syft:package:language","value":"go"},{"name":"syft:package:type","value":"go-module"},{"name":"syft:package:metadataType","value":"go-module-entry"},{"name":"syft:location:0:path","value":"/examples/go.mod"}]},{"bom-ref":"pkg:golang/golang.org/x/term@v0.2.0?package-id=d74c07e5a468b2ec","type":"library","name":"golang.org/x/term","version":"v0.2.0","cpe":"cpe:2.3:a:golang:x\\/term:v0.2.0:*:*:*:*:*:*:*","purl":"pkg:golang/golang.org/x/term@v0.2.0","properties":[{"name":"syft:package:foundBy","value":"go-module-file-cataloger"},{"name":"syft:package:language","value":"go"},{"name":"syft:package:type","value":"go-module"},{"name":"syft:package:metadataType","value":"go-module-entry"},{"name":"syft:location:0:path","value":"/log/log15/go.mod"},{"name":"syft:metadata:h1Digest","value":"h1:z85xZCsEl7bi/KwbNADeBYoOP0++7W1ipu+aGnpwzRM="}]},{"bom-ref":"pkg:golang/google.golang.org/protobuf@v1.31.0?package-id=aa6568cb2df21615","type":"library","name":"google.golang.org/protobuf","version":"v1.31.0","cpe":"cpe:2.3:a:google:protobuf:v1.31.0:*:*:*:*:*:*:*","purl":"pkg:golang/google.golang.org/protobuf@v1.31.0","properties":[{"name":"syft:package:foundBy","value":"go-module-file-cataloger"},{"name":"syft:package:language","value":"go"},{"name":"syft:package:type","value":"go-module"},{"name":"syft:package:metadataType","value":"go-module-entry"},{"name":"syft:location:0:path","value":"/examples/go.mod"},{"name":"syft:metadata:h1Digest","value":"h1:g0LDEJHgrBl9N9r17Ru3sqWhkIx2NB67okBHPwC7hs8="}]},{"bom-ref":"pkg:golang/google.golang.org/protobuf@v1.31.0?package-id=0d41edf73f1d4d9f","type":"library","name":"google.golang.org/protobuf","version":"v1.31.0","cpe":"cpe:2.3:a:google:protobuf:v1.31.0:*:*:*:*:*:*:*","purl":"pkg:golang/google.golang.org/protobuf@v1.31.0","properties":[{"name":"syft:package:foundBy","value":"go-module-file-cataloger"},{"name":"syft:package:language","value":"go"},{"name":"syft:package:type","value":"go-module"},{"name":"syft:package:metadataType","value":"go-module-entry"},{"name":"syft:location:0:path","value":"/go.mod"},{"name":"syft:metadata:h1Digest","value":"h1:g0LDEJHgrBl9N9r17Ru3sqWhkIx2NB67okBHPwC7hs8="}]},{"bom-ref":"pkg:golang/gopkg.in/yaml.v2@v2.4.0?package-id=15848299ac4cecd4","type":"library","name":"gopkg.in/yaml.v2","version":"v2.4.0","purl":"pkg:golang/gopkg.in/yaml.v2@v2.4.0","properties":[{"name":"syft:package:foundBy","value":"go-module-file-cataloger"},{"name":"syft:package:language","value":"go"},{"name":"syft:package:type","value":"go-module"},{"name":"syft:package:metadataType","value":"go-module-entry"},{"name":"syft:location:0:path","value":"/go.mod"},{"name":"syft:metadata:h1Digest","value":"h1:D8xgwECY7CYvx+Y2n4sBz93Jn9JRvxdiyyo8CTfuKaY="}]},{"bom-ref":"pkg:golang/gopkg.in/yaml.v3@v3.0.1?package-id=716c668b92999095","type":"library","name":"gopkg.in/yaml.v3","version":"v3.0.1","cpe":"cpe:2.3:a:yaml_project:yaml:v3.0.1:*:*:*:*:go:*:*","purl":"pkg:golang/gopkg.in/yaml.v3@v3.0.1","properties":[{"name":"syft:package:foundBy","value":"go-module-file-cataloger"},{"name":"syft:package:language","value":"go"},{"name":"syft:package:type","value":"go-module"},{"name":"syft:package:metadataType","value":"go-module-entry"},{"name":"syft:location:0:path","value":"/go.mod"},{"name":"syft:metadata:h1Digest","value":"h1:fxVm/GzAzEWqLHuvctI91KS9hhNmmWOoWu0XTYJS7CA="}]}]}
