{"$schema":"http://cyclonedx.org/schema/bom-1.5.schema.json","bomFormat":"CycloneDX","specVersion":"1.5","serialNumber":"urn:uuid:d2fc25b9-70c6-4aa4-aa24-a8b38b4c3600","version":1,"metadata":{"timestamp":"2024-08-28T16:01:36Z","tools":{"components":[{"type":"application","author":"anchore","name":"syft","version":"1.11.0"}]},"component":{"bom-ref":"33dec84eaab55bb8","type":"file","name":"github.com/semrush/zenrpc"}},"components":[{"bom-ref":"pkg:golang/github.com/gorilla/websocket@v1.4.2?package-id=545908d03b864ea0","type":"library","name":"github.com/gorilla/websocket","version":"v1.4.2","cpe":"cpe:2.3:a:gorilla:websocket:v1.4.2:*:*:*:*:*:*:*","purl":"pkg:golang/github.com/gorilla/websocket@v1.4.2","properties":[{"name":"syft:package:foundBy","value":"go-module-file-cataloger"},{"name":"syft:package:language","value":"go"},{"name":"syft:package:type","value":"go-module"},{"name":"syft:package:metadataType","value":"go-module-entry"},{"name":"syft:location:0:path","value":"/go.mod"},{"name":"syft:metadata:h1Digest","value":"h1:+/TMaTYc4QFitKJxsQ7Yye35DkWvkdLcvGKqM+x0Ufc="}]},{"bom-ref":"pkg:golang/github.com/prometheus/client_golang@v1.7.1?package-id=08481a3521a0b014","type":"library","name":"github.com/prometheus/client_golang","version":"v1.7.1","cpe":"cpe:2.3:a:prometheus:client-golang:v1.7.1:*:*:*:*:*:*:*","purl":"pkg:golang/github.com/prometheus/client_golang@v1.7.1","properties":[{"name":"syft:package:foundBy","value":"go-module-file-cataloger"},{"name":"syft:package:language","value":"go"},{"name":"syft:package:type","value":"go-module"},{"name":"syft:package:metadataType","value":"go-module-entry"},{"name":"syft:cpe23","value":"cpe:2.3:a:prometheus:client_golang:v1.7.1:*:*:*:*:*:*:*"},{"name":"syft:location:0:path","value":"/go.mod"},{"name":"syft:metadata:h1Digest","value":"h1:NTGy1Ja9pByO+xAeH/qiWnLrKtr3hJPNjaVUwnjpdpA="}]},{"bom-ref":"pkg:golang/github.com/smartystreets/goconvey@v1.6.4?package-id=840aca84a9173a6d","type":"library","name":"github.com/smartystreets/goconvey","version":"v1.6.4","cpe":"cpe:2.3:a:smartystreets:goconvey:v1.6.4:*:*:*:*:*:*:*","purl":"pkg:golang/github.com/smartystreets/goconvey@v1.6.4","properties":[{"name":"syft:package:foundBy","value":"go-module-file-cataloger"},{"name":"syft:package:language","value":"go"},{"name":"syft:package:type","value":"go-module"},{"name":"syft:package:metadataType","value":"go-module-entry"},{"name":"syft:location:0:path","value":"/go.mod"},{"name":"syft:metadata:h1Digest","value":"h1:fv0U8FUIMPNf1L9lnHLvLhgicrIVChEkdzIKYqbNC9s="}]},{"bom-ref":"pkg:golang/github.com/thoas/go-funk@v0.6.0?package-id=69498785c64adb36","type":"library","name":"github.com/thoas/go-funk","version":"v0.6.0","cpe":"cpe:2.3:a:thoas:go-funk:v0.6.0:*:*:*:*:*:*:*","purl":"pkg:golang/github.com/thoas/go-funk@v0.6.0","properties":[{"name":"syft:package:foundBy","value":"go-module-file-cataloger"},{"name":"syft:package:language","value":"go"},{"name":"syft:package:type","value":"go-module"},{"name":"syft:package:metadataType","value":"go-module-entry"},{"name":"syft:cpe23","value":"cpe:2.3:a:thoas:go_funk:v0.6.0:*:*:*:*:*:*:*"},{"name":"syft:location:0:path","value":"/go.mod"},{"name":"syft:metadata:h1Digest","value":"h1:ryxN0pa9FnI7YHgODdLIZ4T6paCZJt8od6N9oRztMxM="}]},{"bom-ref":"pkg:golang/golang.org/x/tools@v0.0.0-20200729173947-1c30660f9f89?package-id=a1a577ad04ac4d5b","type":"library","name":"golang.org/x/tools","version":"v0.0.0-20200729173947-1c30660f9f89","cpe":"cpe:2.3:a:golang:x\\/tools:v0.0.0-20200729173947-1c30660f9f89:*:*:*:*:*:*:*","purl":"pkg:golang/golang.org/x/tools@v0.0.0-20200729173947-1c30660f9f89","properties":[{"name":"syft:package:foundBy","value":"go-module-file-cataloger"},{"name":"syft:package:language","value":"go"},{"name":"syft:package:type","value":"go-module"},{"name":"syft:package:metadataType","value":"go-module-entry"},{"name":"syft:location:0:path","value":"/go.mod"},{"name":"syft:metadata:h1Digest","value":"h1:Vr0/urnX/81QM48v4snko5AmpNh2rTiepXMSvBRZ4Xg="}]}]}
